Workbook

Sheet DICCIONARIO
A1: Nombre columna | B1: Hoja origen | C1: Descripción | D1: Tipo de dato | E1: Valores posibles / Ejemplo | F1: Reglas de llenado | G1: Edición restringida | H1: Validaciones | I1: Origen / Relación con otra hoja | J1: Observaciones
A2: ContenidoID | B2: CONTENIDOS_PRODUCIDOS | C2: Identificador único asignado a cada contenido producido en el sistema. Permite diferenciarlo, relacionarlo con otros registros y evitar duplicidades. | D2: Texto alfanumérico único, sin repetir (se autocompleta) | E2: CONT1, CONT2, CONT3 | F2: Se completa automáticamente por script al ingresar el Título | G2: Solo editable por script; no se permite edición manual. | H2: Valor único, no permite duplicados. Generado automáticamente.
A3: Titulo | B3: CONTENIDOS_PRODUCIDOS | C3: Nombre principal del contenido. Debe ser claro y conciso, representando de manera directa lo que el contenido ofrece o aborda. | D3: Texto | E3: Ejemplo: "Gráficos cartesianos", "Estadística" | F3: Obligatorio | G3: Área responsable de la carga. (GOICE) | H3: Campo de texto. No permite valores vacíos.
A4: Descripcion | B4: CONTENIDOS_PRODUCIDOS | C4: Resumen explicativo del contenido. Detalla temática, objetivos, puntos centrales y palabras clave asociadas. Permite que otros usuarios lo identifiquen fácilmente y comprendan su utilidad. | D4: Texto largo | E4: Ejemplo: "Secuencia didáctica sobre energías renovables para secundaria”; “Juego interactivo para practicar suma y resta de fracciones". | F4: Obligatorio. Incluir tema, objetivo y palabras clave | G4: Área responsable de la carga. (GOICE) | H4: Campo de texto largo. No permite valores vacíos.
A5: TipoContenido_Nombre | B5: CONTENIDOS_PRODUCIDOS | C5: Clasificación del contenido según su naturaleza y formato. Se selecciona de una lista predefinida y ayuda a organizar, filtrar y buscar materiales similares. | D5: Selección desplegable (texto) | E5: Valores posibles: Módulo, Módulo Interactivo, Juego educativo, Infografía interactiva, Microcontenido, Evaluación formativa, Contenido Curricular, Secuencia Didáctica, Recurso Interactivo, Video, Texto, Actividad Integradora, Cuestionario, Prueba, Curso, Unidad | F5: Obligatorio. Seleccionar del desplegable. | G5: Área responsable de la carga. (GOICE) | H5: Lista desplegable desde la hoja TIPO_CONTENIDO. Solo permite valores de la lista. | I5: TIPO_CONTENIDO | J5: Si el tipo de contenido que necesitás no aparece en el desplegable, solicitá su incorporación en la hoja TIPO_CONTENIDO.
A6: TipoContenidoID | B6: CONTENIDOS_PRODUCIDOS | C6: Código identificador del tipo de contenido. Se genera o completa automáticamente al seleccionar el nombre de tipo y sirve para establecer relaciones técnicas entre registros. | D6: Texto alfanumérico (se autocompleta) | E6: Ejemplo: TCON1, TCON2, TCON3 | F6: Se autocompleta. No editar manualmente. | G6: Solo editable por sistema/autocompletado. | H6: Autocompletado por fórmula desde TIPO_CONTENIDO según TipoContenido_Nombre. | I6: TIPO_CONTENIDO | J6: No editar manualmente. Si hay inconsistencias, revisar la hoja TIPO_CONTENIDO.
A7: Nombre_proveedor | B7: CONTENIDOS_PRODUCIDOS | C7: Nombre de la persona, empresa, equipo o área que desarrolló o brindó el contenido. Se elige desde un listado ya existente para garantizar precisión y facilitar búsqueda por proveedor. | D7: Selección desplegable (texto) | E7: Ejemplo: Khan Academy, Ticmas | F7: Obligatorio. Seleccionar del desplegable. | G7: Área responsable de la carga. (GOICE) | H7: Lista desplegable desde la hoja PROVEEDORES. Solo permite valores de la lista. | I7: PROVEEDORES | J7: Si el proveedor no figura en el desplegable, solicitá su alta en la hoja PROVEEDORES antes de continuar.
A8: ProveedorID | B8: CONTENIDOS_PRODUCIDOS | C8: Código único que identifica al proveedor. Se autocompleta al elegir el nombre del proveedor y permite relacionar el contenido con información ampliada del proveedor en la base de datos. | D8: Texto alfanumérico (se autocompleta) | E8: Ejemplo: PROV1, PROV2, PROV3 | F8: Se autocompleta. No editar manualmente. | G8: Solo editable por sistema/autocompletado. | H8: Autocompletado por fórmula desde PROVEEDORES según Nombre_proveedor. | I8: PROVEEDORES | J8: No editar manualmente. Si hay inconsistencias, revisar la hoja PROVEEDORES.
A9: URL_Contenido | B9: CONTENIDOS_PRODUCIDOS | C9: Enlace directo en internet donde puede consultarse, visualizarse o descargarse el contenido. Permite acceder rápidamente al material desde la base de datos. | D9: URL (texto) | E9: Ejemplo: https://rise.articulate.com/share/agPj3vmKBvLlcQys3ZdJxRGrNN9ZagD4 | F9: Obligatorio para contenidos digitales. Formato URL válida. | G9: Área responsable de la carga. (GOICE) | H9: Formato URL válida (debe comenzar con http:// o https://).
A10: Licencia | B10: CONTENIDOS_PRODUCIDOS | C10: Tipo de permiso o autorización bajo la que puede utilizarse el contenido: puede ser libre, restringida, educativa, etc. Brinda claridad sobre el uso permitido y las condiciones legales. | D10: Selección desplegable o texto breve | E10: Valores posibles/ejemplo: Creative Commons, Licencia educativa, Copyright institucional | F10: Opcional. Completar si corresponde. | G10: Área responsable de la carga. (GOICE) | H10: Campo de texto o lista desplegable según valores predefinidos. Permite vacío.
A11: Modalidad_Tipo | B11: CONTENIDOS_PRODUCIDOS | C11: Conjunto de modalidades educativas asociadas al contenido. Puede incluir una o varias opciones entre Bachiller Común A, Bachiller Común B y Técnica. Los valores disponibles provienen de la hoja MODALIDADES. La selección de modalidad habilita la elección de espacios curriculares vinculados en la columna siguiente. | D11: Selección desplegable múltiple (texto) | E11: Valores posibles: Bachiller Común A, Bachiller Común B, Técnica (pueden seleccionarse uno o varios a la vez) | F11: Obligatorio. Seleccionar una o más opciones. Habilita la columna siguiente. | G11: Área responsable de la carga. (GOICE) | H11: Lista desplegable múltiple desde la hoja MODALIDADES. Permite selección múltiple. | I11: MODALIDADES | J11: Si necesitás agregar una nueva modalidad, solicitá su incorporación en la hoja MODALIDADES.
A12: Nombre_Espacio_curricular | B12: CONTENIDOS_PRODUCIDOS | C12: Denominación del espacio curricular (materia) correspondiente según la modalidad educativa seleccionada. Los valores disponibles se obtienen de la hoja ESPACIOS_CURRICULARES. | D12: Selección desplegable (texto) | E12: Ejemplo: Matemática, Lengua y Literatura, Física, Historia, Inglés | F12: Obligatorio. Se habilita tras seleccionar Modalidad_Tipo. | G12: Área responsable de la carga. (GOICE) | H12: Lista desplegable desde la hoja ESPACIO_CURRICULAR_SA, filtrada según Modalidad_Tipo seleccionada. | I12: ESPACIO_CURRICULAR_SA | J12: Si el espacio curricular no aparece en el desplegable según la modalidad elegida, solicitá su incorporación en la hoja ESPACIO_CURRICULAR_SA. Importante: El desplegable se genera automáticamente según la modalidad seleccionada. Si el desplegable no aparece de inmediato, no escriban el valor manualmente. Esperen unos segundos o cambien de celda y vuelvan a seleccionarla.
A13: ID_Espacio_curricular | B13: CONTENIDOS_PRODUCIDOS | C13: Identificador único asociado al espacio curricular seleccionado. Se autocompleta al elegir el nombre y se relaciona con la hoja ESPACIOS_CURRICULARES. | D13: Texto alfanumérico (se autocompleta) | E13: Ejemplo: ECURR1, ECURR2, ECURR3 | F13: Se autocompleta. No editar manualmente. | G13: Solo editable por sistema/autocompletado. | H13: Autocompletado por fórmula desde ESPACIO_CURRICULAR_SA según Nombre_Espacio_curricular. | I13: ESPACIO_CURRICULAR_SA | J13: No editar manualmente. Si hay inconsistencias, revisar la hoja ESPACIO_CURRICULAR_SA.
A14: Bimestre_Aplicacion | B14: CONTENIDOS_PRODUCIDOS | C14: Periodo del año escolar en el que está previsto implementar el contenido. Suele referirse a uno de los bimestres o etapas definidas en el calendario académico. | D14: Selección múltiple desplegable (texto) | E14: Valores posibles: 1, 2, 3, 4, Anual | F14: Obligatorio. Indicar período escolar. | G14: Área responsable de la carga. (GOICE) | H14: Lista desplegable con valores predefinidos. Solo permite valores de la lista.
A15: Link_contenido_priorizado | B15: CONTENIDOS_PRODUCIDOS | C15: Enlace al documento curricular oficial donde se detallan los contenidos priorizados para el espacio curricular correspondiente. Este documento es la referencia que se utilizó para orientar la producción del contenido. | D15: URL (texto) | E15: Ejemplo: https://buenosaires.gob.ar/sites/default/files/2025-08/CONTENIDOS_PRIORIZADOS_FG.pdf | F15: Obligatorio si existe documento de contenidos priorizados para el espacio curricular. Debe completarse con un enlace válido. | G15: Área responsable de la carga. (GOICE) | H15: Formato URL válida, debe empezar con http:// o https://
A16: Destinatario | B16: CONTENIDOS_PRODUCIDOS | C16: Grupo o colectivo principal al que va dirigido el contenido. Los valores posibles incluyen alumnos, docentes y familias. Las opciones provienen de una lista predefinida. | D16: Selección desplegable (texto) | E16: Valores posibles: Alumnos, Docentes, Familias | F16: Obligatorio. Seleccionar del desplegable. | G16: Área responsable de la carga. (GOICE) | H16: Lista desplegable con valores: Alumnos, Docentes, Familias. Solo permite valores de la lista.
A17: Estado_Revision | B17: CONTENIDOS_PRODUCIDOS | C17: Estado actual del proceso de revisión del contenido, según las opciones establecidas en una lista desplegable. Permite conocer el avance y seguimiento de validaciones. | D17: Selección desplegable (texto) | E17: Valores posibles/ejemplo: En revisión, Aprobado, Requiere ajustes, No aprobado | F17: Obligatorio. Seleccionar del desplegable. | G17: Área responsable de la carga. (GOICE) | H17: Lista desplegable con valores predefinidos de estados de revisión. Solo permite valores de la lista.
A18: Area_ministerio_revisor | B18: CONTENIDOS_PRODUCIDOS | C18: Nombre del área ministerial responsable por la revisión del contenido. Identifica la dirección, gerencia o sector que realizó la validación. Las opciones provienen de una lista predefinida. | D18: Selección desplegable (texto) | E18: Ejemplo: GOICE - Gerencia Operativa de Innovación y Contenidos Educativos | F18: Obligatorio si el contenido fue revisado. | G18: Área responsable de la carga. (GOICE) | H18: Campo de texto o lista desplegable según áreas ministeriales registradas.
A19: Apellidos_nombres_revisor | B19: CONTENIDOS_PRODUCIDOS | C19: Identificación del responsable de la revisión a través de apellido y nombre. Los valores se seleccionan de un desplegable alimentado por la hoja ACTORES, la cual debe estar previamente completada con las personas habilitadas para la revisión. | D19: Selección desplegable (texto) | E19: Ejemplo: García, Ana; López, María del Carmen; Pérez, Juan | F19: Obligatorio si el contenido fue revisado. Seleccionar del desplegable. | G19: Área responsable de la carga. (GOICE) | H19: Lista desplegable desde la hoja ACTORES. Solo permite valores de la lista. | I19: ACTORES | J19: Si el revisor no figura en el desplegable, solicitá su alta en la hoja ACTORES.
A20: Actor_ID | B20: CONTENIDOS_PRODUCIDOS | C20: Código único vinculado al revisor seleccionado. Se autocompleta a partir de la selección de Apellidos_nombres_revisor y de la hoja donde figuran los revisores. | D20: Texto alfanumérico (se autocompleta) | E20: Ejemplo: ACT1, ACT2, ACT3 | F20: Se autocompleta. No editar manualmente. | G20: Solo editable por sistema/autocompletado. | H20: Autocompletado por fórmula desde ACTORES según Apellidos_nombres_revisor. | I20: ACTORES | J20: No editar manualmente. Si hay inconsistencias, revisar la hoja ACTORES.
A21: Fecha_Revision | B21: CONTENIDOS_PRODUCIDOS | C21: Fecha en que se realizó la última revisión del contenido. Debe actualizarse cada vez que se modifica el estado de revisión. | D21: Fecha (formato fecha válida) | E21: Ejemplo: 20/10/2025 | F21: Obligatorio al cambiar Estado_Revision. Formato dd/mm/aaaa. | G21: Área responsable de la carga. (GOICE y GOED) | H21: Formato fecha válida (dd/mm/aaaa). No permite fechas futuras o valores de texto.
A22: Calificacion_Calidad | B22: CONTENIDOS_PRODUCIDOS | C22: Valoración asignada a la calidad del contenido tras la revisión, según criterios internos. Se selecciona entre opciones predefinidas en una lista desplegable. | D22: Selección desplegable (texto) | E22: Valores posibles/ejemplo: Alta, Media, Baja; Excelente, Satisfactorio, Insuficiente | F22: Obligatorio tras revisión. Seleccionar del desplegable. | G22: Área responsable de la carga. (GOICE) | H22: Lista desplegable con valores predefinidos de calificación. Solo permite valores de la lista.
A23: Vigencia_Desde | B23: CONTENIDOS_PRODUCIDOS | C23: Fecha a partir de la cual el contenido puede ser publicado, distribuido o utilizado oficialmente. Permite establecer desde cuándo está vigente su uso. | D23: Fecha (formato fecha válida) | E23: Ejemplo: 20/10/2025 | F23: Obligatorio. Formato dd/mm/aaaa. | G23: Área responsable de la carga. (GOICE) | H23: Formato fecha válida (dd/mm/aaaa). No permite valores de texto.
A24: Vigencia_Hasta | B24: CONTENIDOS_PRODUCIDOS | C24: Fecha límite hasta la que el contenido mantiene su validez para ser utilizado, consultado o distribuido. Tras esta fecha puede considerarse obsoleto o necesitar revisión | D24: Fecha (formato fecha válida) | E24: Ejemplo: 20/10/2025 | F24: Opcional. Formato dd/mm/aaaa. | G24: Área responsable de la carga. (GOICE) | H24: Formato fecha válida (dd/mm/aaaa). Debe ser posterior a Vigencia_Desde si se completa.
A25: Estado | B25: CONTENIDOS_PRODUCIDOS | C25: Situación actual del contenido dentro del sistema. Los valores posibles incluyen, entre otros: Activo, En desarrollo, Pendiente, Suspendido, Inactivo y Obsoleto. Permite conocer de un vistazo si el contenido está disponible, en proceso o ya no debe utilizarse. Los valores se seleccionan de una lista desplegable predefinida. | D25: Selección desplegable (texto) | E25: Valores posibles/ejemplo: Alta, Media, Baja; Excelente, Satisfactorio, Insuficiente | F25: Obligatorio. Seleccionar del desplegable. | G25: Área responsable de la carga. (GOED) | H25: Lista desplegable con valores: Activo, En desarrollo, Pendiente, Suspendido, Inactivo, Obsoleto. Solo permite valores de la lista.

Sheet CONTENIDOS_PRODUCIDOS
A1: ContenidoID | B1: Titulo | C1: Descripcion | D1: TipoContenido_Nombre | E1: TipoContenidoID | F1: Nombre_proveedor | G1: ProveedorID | H1: URL_Contenido | I1: Licencia | J1: Modalidad_Tipo | K1: Nombre_Espacio_curricular | L1: ID_Espacio_curricular | M1: Bimestre_Aplicacion | N1: Link_contenido_priorizado | O1: Destinatario | P1: Estado_Revision | Q1: Area_ministerio_revisor | R1: Apellidos_nombres_revisor | S1: Actor_ID | T1: Fecha_Revision | U1: Calificacion_Calidad | V1: Vigencia_Desde | W1: Vigencia_Hasta | X1: Estado
A2: CONT1 | B2: Números naturales y números enteros | C2: Descripción contenido 1 | E2: {=IF(D2:D1000 = "", "", IFERROR( INDEX( TIPO_CONTENIDO!A$2:A$17, MATCH(D2:D1000, TIPO_CONTENIDO!B$2:B$17, 0) ) ,"") )} | F2: Ticmas | G2: {=IFERROR( IF(F2="","",INDEX(PROVEEDORES!$A$2:$A$11, MATCH(F2, PROVEEDORES!$B$2:$B$11, 0))) ,"")} -> PROV2 | H2: https://rise.articulate.com/share/agPj3vmKBvLlcQys3ZdJxRGrNN9ZagD4 | J2: Bachiller Común A | K2: Matemática I | L2: ECURR3 | M2: 1 | P2: Publicado | Q2: GOICE - Gerencia Operativa de Innovación y Contenidos Educativos | T2: 45950 | X2: En desarrollo
A3: CONT2 | B3: Gráficos cartesianos | C3: Descripción contenido 2 | F3: Ticmas | G3: {=IFERROR( IF(F3="","",INDEX(PROVEEDORES!$A$2:$A$11, MATCH(F3, PROVEEDORES!$B$2:$B$11, 0))) ,"")} -> PROV2 | H3: https://rise.articulate.com/share/M9udTVX6crIZIcStC_uEpHQWwpzRHtMt | J3: Bachiller Común A | K3: Matemática II | L3: ECURR12 | M3: 2
A4: CONT3 | B4: Triángulos | C4: Descripción contenido 3 | F4: Ticmas | G4: {=IFERROR( IF(F4="","",INDEX(PROVEEDORES!$A$2:$A$11, MATCH(F4, PROVEEDORES!$B$2:$B$11, 0))) ,"")} -> PROV2 | H4: https://rise.articulate.com/share/GUcJbej46s1ZA1FZTvkx9DQmg8RfyhBu | J4: Bachiller Común A | K4: Laboratorio Ciencias Naturales E + F | L4: ECURR60 | M4: 3
A5: CONT4 | B5: Estadística | C5: Descripción contenido 4 | F5: Ticmas | G5: {=IFERROR( IF(F5="","",INDEX(PROVEEDORES!$A$2:$A$11, MATCH(F5, PROVEEDORES!$B$2:$B$11, 0))) ,"")} -> PROV2 | H5: https://rise.articulate.com/share/RdMmbP1ee-UzvrizvIDQilT4XP0ZzD7Y | J5: Bachiller Común A | M5: 4
A6: CONT5 | B6: Divisibilidad | F6: Ticmas | G6: {=IFERROR( IF(F6="","",INDEX(PROVEEDORES!$A$2:$A$11, MATCH(F6, PROVEEDORES!$B$2:$B$11, 0))) ,"")} -> PROV2 | H6: https://rise.articulate.com/share/dfqrz0psYSWFqsRPU9xlTkznSYpO8gOB | J6: Bachiller Común A | M6: 1
A7: CONT6 | B7: Función lineal | F7: Ticmas | G7: {=IFERROR(IF(F7="","",INDEX(PROVEEDORES!$A$2:$A$11, MATCH(F7, PROVEEDORES!$B$2:$B$11, 0))),"")} -> PROV2 | H7: https://rise.articulate.com/share/KEEpEeXkxXcuXtLeWXEW2QB_p3KAfW9z | M7: 2
A8: CONT7 | B8: Cuadriláteros y Teorema de Thales | F8: Ticmas | G8: {=IFERROR( IF(F8="","",INDEX(PROVEEDORES!$A$2:$A$11, MATCH(F8, PROVEEDORES!$B$2:$B$11, 0))) ,"")} -> PROV2 | H8: https://rise.articulate.com/share/B6m8OvP-au9QNFu6bOBsbdbnBZfgpHHv | M8: 3
A9: CONT8 | B9: Estadística | F9: Ticmas | G9: {=IFERROR( IF(F9="","",INDEX(PROVEEDORES!$A$2:$A$11, MATCH(F9, PROVEEDORES!$B$2:$B$11, 0))) ,"")} -> PROV2 | H9: https://rise.articulate.com/share/mmju6v4Q8k5X9AKjNJqqhXWdbGWYJ2g- | M9: 4
A10: CONT9 | B10: Problemas de conteo | F10: Ticmas | G10: {=IFERROR( IF(F10="","",INDEX(PROVEEDORES!$A$2:$A$11, MATCH(F10, PROVEEDORES!$B$2:$B$11, 0))) ,"")} -> PROV2 | H10: https://rise.articulate.com/share/wQPuomNeawd3pJRmOicTkpFlIHxRA6WZ | M10: 1
A11: CONT10 | B11: Sistema de ecuaciones | F11: Ticmas | G11: {=IFERROR( IF(F11="","",INDEX(PROVEEDORES!$A$2:$A$11, MATCH(F11, PROVEEDORES!$B$2:$B$11, 0))) ,"")} -> PROV2 | H11: https://rise.articulate.com/share/mg_wg364uyYU2ZCGqH0Fy0dQRUR5E_qL | M11: 2
A12: CONT11 | B12: Razones trigonométricas | F12: Ticmas | G12: {=IFERROR( IF(F12="","",INDEX(PROVEEDORES!$A$2:$A$11, MATCH(F12, PROVEEDORES!$B$2:$B$11, 0))) ,"")} -> PROV2 | H12: https://rise.articulate.com/share/m2KTACWWvrDbw2ZePqr7vwHcwsM1xzgj | M12: 3
A13: CONT12 | B13: Función cuadrática | F13: Ticmas | G13: {=IFERROR( IF(F13="","",INDEX(PROVEEDORES!$A$2:$A$11, MATCH(F13, PROVEEDORES!$B$2:$B$11, 0))) ,"")} -> PROV2 | H13: https://rise.articulate.com/share/eZUjzyVb2Cbo8Ru3oMH9c9AEU5-h4U1o | M13: 4
A14: CONT13 | B14: Errores en la medición. Sucesiones | F14: Ticmas | G14: {=IFERROR( IF(F14="","",INDEX(PROVEEDORES!$A$2:$A$11, MATCH(F14, PROVEEDORES!$B$2:$B$11, 0))) ,"")} -> PROV2 | H14: https://rise.articulate.com/share/o5gcsGusU5Iz-qcZL_VhetWxn_LJf2oZ | M14: 1
A15: CONT14 | B15: Funciones polinómicas | F15: Ticmas | G15: {=IFERROR( IF(F15="","",INDEX(PROVEEDORES!$A$2:$A$11, MATCH(F15, PROVEEDORES!$B$2:$B$11, 0))) ,"")} -> PROV2 | H15: https://rise.articulate.com/share/RVF7Uxu_yCsI638Z6aG7zlL2u7detRQZ | M15: 2
A16: CONT15 | B16: Funciones exponenciales y logarítmicas | F16: Ticmas | G16: {=IFERROR( IF(F16="","",INDEX(PROVEEDORES!$A$2:$A$11, MATCH(F16, PROVEEDORES!$B$2:$B$11, 0))) ,"")} -> PROV2 | H16: https://rise.articulate.com/share/4sz75xkf6tOHhhm2sjwe5zSNSmsRK6Ng | M16: 3
A17: CONT16 | B17: Probabilidad | F17: Ticmas | G17: {=IFERROR( IF(F17="","",INDEX(PROVEEDORES!$A$2:$A$11, MATCH(F17, PROVEEDORES!$B$2:$B$11, 0))) ,"")} -> PROV2 | H17: https://rise.articulate.com/share/ftavUKc1CDpY_IraL04bi8dZcdyU5dCx | M17: 4
A18: CONT17 | B18: Ecuaciones e inecuaciones | F18: Ticmas | G18: {=IFERROR( IF(F18="","",INDEX(PROVEEDORES!$A$2:$A$11, MATCH(F18, PROVEEDORES!$B$2:$B$11, 0))) ,"")} -> PROV2 | H18: https://rise.articulate.com/share/lH2-yrBVRRZN1tqArgi27zY5-MlpO5K7 | M18: 1
A19: CONT18 | B19: Funciones racionales | F19: Ticmas | G19: {=IFERROR( IF(F19="","",INDEX(PROVEEDORES!$A$2:$A$11, MATCH(F19, PROVEEDORES!$B$2:$B$11, 0))) ,"")} -> PROV2 | H19: https://rise.articulate.com/share/zcdgf7Whd61IbZeYpNXe6cBm-Yqp7rIT | M19: 2
... A41: CONT40 | B41: Leer, pensar y escribir en clave académica | F41: Ticmas | G41: {=IFERROR( IF(F41="","",INDEX(PROVEEDORES!$A$2:$A$11, MATCH(F41, PROVEEDORES!$B$2:$B$11, 0))) ,"")} -> PROV2 | H41: https://rise.articulate.com/share/VjplWy-rd3ooimV8iN4c2kNWU2LnZQbf | M41: 4
A42: CONT41 | B42: La vida escolar (1.1) | F42: Ticmas | G42: {=IFERROR( IF(F42="","",INDEX(PROVEEDORES!$A$2:$A$11, MATCH(F42, PROVEEDORES!$B$2:$B$11, 0))) ,"")} -> PROV2 | M42: 1
A43: CONT42 | B43: Conociéndonos y cuidando nuestro entorno (1.2) | F43: Ticmas | G43: {=IFERROR( IF(F43="","",INDEX(PROVEEDORES!$A$2:$A$11, MATCH(F43, PROVEEDORES!$B$2:$B$11, 0))) ,"")} -> PROV2 | M43: 2
A44: CONT43 | B44: Intereses personales y preferencias (1.3) | F44: Ticmas | G44: {=IFERROR( IF(F44="","",INDEX(PROVEEDORES!$A$2:$A$11, MATCH(F44, PROVEEDORES!$B$2:$B$11, 0))) ,"")} -> PROV2 | M44: 3
A45: CONT44 | B45: Cuidando el medio ambiente (1.4) | F45: Ticmas | G45: {=IFERROR( IF(F45="","",INDEX(PROVEEDORES!$A$2:$A$11, MATCH(F45, PROVEEDORES!$B$2:$B$11, 0))) ,"")} -> PROV2 | M45: 4
A46: CONT45 | B46: Hábitos alimenticios (2.1) | F46: Ticmas | G46: {=IFERROR( IF(F46="","",INDEX(PROVEEDORES!$A$2:$A$11, MATCH(F46, PROVEEDORES!$B$2:$B$11, 0))) ,"")} -> PROV2 | M46: 1
A47: CONT46 | B47: Historias y recuerdos (2.2) | F47: Ticmas | G47: {=IFERROR( IF(F47="","",INDEX(PROVEEDORES!$A$2:$A$11, MATCH(F47, PROVEEDORES!$B$2:$B$11, 0))) ,"")} -> PROV2 | M47: 2
A48: CONT47 | B48: Armar un presupuesto para una fiesta/evento (2.3) | F48: Ticmas | G48: {=IFERROR( IF(F48="","",INDEX(PROVEEDORES!$A$2:$A$11, MATCH(F48, PROVEEDORES!$B$2:$B$11, 0))) ,"")} -> PROV2 | M48: 3
A49: CONT48 | B49: Making a legendary event epic | F49: Ticmas | G49: {=IFERROR( IF(F49="","",INDEX(PROVEEDORES!$A$2:$A$11, MATCH(F49, PROVEEDORES!$B$2:$B$11, 0))) ,"")} -> PROV2 | M49: 4
A50: CONT49 | B50: Contar historias y compartir experiencias (3.1) | F50: Ticmas | G50: {=IFERROR( IF(F50="","",INDEX(PROVEEDORES!$A$2:$A$11, MATCH(F50, PROVEEDORES!$B$2:$B$11, 0))) ,"")} -> PROV2 | M50: 1
A51: CONT50 | B51: Compartir opiniones y dar consejos (3.2) | F51: Ticmas | G51: {=IFERROR( IF(F51="","",INDEX(PROVEEDORES!$A$2:$A$11, MATCH(F51, PROVEEDORES!$B$2:$B$11, 0))) ,"")} -> PROV2 | M51: 2
A52: CONT51 | B52: Argumentando nuestras ideas y valores (3.3) | F52: Ticmas | G52: {=IFERROR( IF(F52="","",INDEX(PROVEEDORES!$A$2:$A$11, MATCH(F52, PROVEEDORES!$B$2:$B$11, 0))) ,"")} -> PROV2 | M52: 3
A53: CONT52 | B53: Relate events in chronological order (3.4) | F53: Ticmas | G53: {=IFERROR( IF(F53="","",INDEX(PROVEEDORES!$A$2:$A$11, MATCH(F53, PROVEEDORES!$B$2:$B$11, 0))) ,"")} -> PROV2 | M53: 4
... A89: CONT88 | B89: Juger | F89: Ticmas | G89: {=IFERROR( IF(F89="","",INDEX(PROVEEDORES!$A$2:$A$11, MATCH(F89, PROVEEDORES!$B$2:$B$11, 0))) ,"")} -> PROV2 | M89: 4
A90: CONT89 | B90: Cómo llega el agua a mi vaso A | F90: Ticmas | G90: {=IFERROR( IF(F90="","",INDEX(PROVEEDORES!$A$2:$A$11, MATCH(F90, PROVEEDORES!$B$2:$B$11, 0))) ,"")} -> PROV2 | H90: https://rise.articulate.com/share/0oIju8xj659PHafjnvmpbkukc9IBtnIu | M90: 1
A91: CONT90 | B91: Cómo llega el agua a mi vaso B | F91: Ticmas | G91: {=IFERROR( IF(F91="","",INDEX(PROVEEDORES!$A$2:$A$11, MATCH(F91, PROVEEDORES!$B$2:$B$11, 0))) ,"")} -> PROV2 | H91: https://rise.articulate.com/share/yH8g84ssRUYCpkXv0qnzyGtKLVCRAEAC | M91: 2
A92: CONT91 | B92: ¿Por qué elegimos representantes en las urnas? A | F92: Ticmas | G92: {=IFERROR( IF(F92="","",INDEX(PROVEEDORES!$A$2:$A$11, MATCH(F92, PROVEEDORES!$B$2:$B$11, 0))) ,"")} -> PROV2 | H92: https://rise.articulate.com/share/Hvr9GswTOyVLFk9SdS0lhglSRsxV42yS | M92: 1
A93: CONT92 | B93: ¿Por qué elegimos representantes en las urnas? B | F93: Ticmas | G93: {=IFERROR( IF(F93="","",INDEX(PROVEEDORES!$A$2:$A$11, MATCH(F93, PROVEEDORES!$B$2:$B$11, 0))) ,"")} -> PROV2 | H93: https://rise.articulate.com/share/iuFmgScgObjuelZDY7s3OB4YTgwKMA37 | M93: 2
A94: CONT93 | B94: ¿Por qué Argentina es un país agroexportador? A | F94: Ticmas | G94: {=IFERROR( IF(F94="","",INDEX(PROVEEDORES!$A$2:$A$11, MATCH(F94, PROVEEDORES!$B$2:$B$11, 0))) ,"")} -> PROV2 | H94: https://rise.articulate.com/share/Nh4Bu82ZaVpso3lulj8BkFf0K46AT-Yb | M94: 1
A95: CONT94 | B95: ¿Por qué Argentina es un país agroexportador? B | F95: Ticmas | G95: {=IFERROR( IF(F95="","",INDEX(PROVEEDORES!$A$2:$A$11, MATCH(F95, PROVEEDORES!$B$2:$B$11, 0))) ,"")} -> PROV2 | H95: https://rise.articulate.com/share/MvBoY070U6OcuWJeQ99oQYg34O1EGxTO | M95: 2
A96: CONT95 | B96: ¿Cómo se produjo la globalización? A | F96: Ticmas | G96: {=IFERROR( IF(F96="","",INDEX(PROVEEDORES!$A$2:$A$11, MATCH(F96, PROVEEDORES!$B$2:$B$11, 0))) ,"")} -> PROV2 | H96: https://rise.articulate.com/share/NDSIanrX2M7zis7yqJimCyQgK46M2-nZ | M96: 1
A97: CONT96 | B97: ¿Cómo se produjo la globalización? B | F97: Ticmas | G97: {=IFERROR( IF(F97="","",INDEX(PROVEEDORES!$A$2:$A$11, MATCH(F97, PROVEEDORES!$B$2:$B$11, 0))) ,"")} -> PROV2 | H97: https://rise.articulate.com/share/5mrVQU6JUm4WQ8GgD6cKXw0Y4TdlqSHe | M97: 2
A98: CONT97 | B98: ¿Siempre somos, a la vez, iguales y diferentes? A | F98: Ticmas | G98: {=IFERROR( IF(F98="","",INDEX(PROVEEDORES!$A$2:$A$11, MATCH(F98, PROVEEDORES!$B$2:$B$11, 0))) ,"")} -> PROV2 | H98: https://rise.articulate.com/share/ur6aNJPoqXt8YTcfGenrxFxEhEuk2RMi | M98: 3
A99: CONT98 | B99: ¿Siempre somos, a la vez, iguales y diferentes? B | F99: Ticmas | G99: {=IFERROR( IF(F99="","",INDEX(PROVEEDORES!$A$2:$A$11, MATCH(F99, PROVEEDORES!$B$2:$B$11, 0))) ,"")} -> PROV2 | H99: https://rise.articulate.com/share/HlnTMJ4ezzcIWWixa4kX6uaowQrR90Ix | M99: 4
A100: CONT99 | B100: ¿Por qué existen las guerras? A | F100: Ticmas | G100: {=IFERROR( IF(F100="","",INDEX(PROVEEDORES!$A$2:$A$11, MATCH(F100, PROVEEDORES!$B$2:$B$11, 0))) ,"")} -> PROV2 | M100: 3
A101: CONT100 | B101: ¿Por qué existen las guerras? B | F101: Ticmas | G101: {=IFERROR( IF(F101="","",INDEX(PROVEEDORES!$A$2:$A$11, MATCH(F101, PROVEEDORES!$B$2:$B$11, 0))) ,"")} -> PROV2 | M101: 4
A102: CONT101 | B102: ¿Por qué ya casi no quedan reyes en el mundo? A | F102: Ticmas | G102: {=IFERROR( IF(F102="","",INDEX(PROVEEDORES!$A$2:$A$11, MATCH(F102, PROVEEDORES!$B$2:$B$11, 0))) ,"")} -> PROV2 | H102: https://rise.articulate.com/share/EJV8EiQSsDBF5yOBRI5MMgoXx-K9xokp | M102: 3
A103: CONT102 | B103: ¿Por qué ya casi no quedan reyes en el mundo? B | F103: Ticmas | G103: {=IFERROR( IF(F103="","",INDEX(PROVEEDORES!$A$2:$A$11, MATCH(F103, PROVEEDORES!$B$2:$B$11, 0))) ,"")} -> PROV2 | M103: 4
A104: CONT103 | B104: ¿Cómo surgieron las ciudades? A | F104: Ticmas | G104: {=IFERROR( IF(F104="","",INDEX(PROVEEDORES!$A$2:$A$11, MATCH(F104, PROVEEDORES!$B$2:$B$11, 0))) ,"")} -> PROV2 | H104: https://rise.articulate.com/share/-pEYN4sNCaPExqoSCQTlAv1vzUrYP9lG | M104: 3
A105: CONT104 | B105: ¿Cómo surgieron las ciudades? B | F105: Ticmas | G105: {=IFERROR( IF(F105="","",INDEX(PROVEEDORES!$A$2:$A$11, MATCH(F105, PROVEEDORES!$B$2:$B$11, 0))) ,"")} -> PROV2 | M105: 4
A106: CONT105 | B106: ¿Qué es el neoliberalismo? A | F106: Ticmas | G106: {=IFERROR( IF(F106="","",INDEX(PROVEEDORES!$A$2:$A$11, MATCH(F106, PROVEEDORES!$B$2:$B$11, 0))) ,"")} -> PROV2 | M106: 3
A107: CONT106 | B107: ¿Qué es el neoliberalismo? B | F107: Ticmas | G107: {=IFERROR( IF(F107="","",INDEX(PROVEEDORES!$A$2:$A$11, MATCH(F107, PROVEEDORES!$B$2:$B$11, 0))) ,"")} -> PROV2 | M107: 4
A108: CONT107 | B108: Causas de los flujos migratorios de los siglos XIX y XX - A | F108: Ticmas | G108: {=IFERROR( IF(F108="","",INDEX(PROVEEDORES!$A$2:$A$11, MATCH(F108, PROVEEDORES!$B$2:$B$11, 0))) ,"")} -> PROV2 | M108: 3
A109: CONT108 | B109: Argentina: de la política al trabajo, 1950-actualidad | F109: Ticmas | G109: {=IFERROR( IF(F109="","",INDEX(PROVEEDORES!$A$2:$A$11, MATCH(F109, PROVEEDORES!$B$2:$B$11, 0))) ,"")} -> PROV2 | M109: 4
A110: CONT109 | B110: La banalidad del mal: los genocidios en el mundo A | F110: Ticmas | G110: {=IFERROR( IF(F110="","",INDEX(PROVEEDORES!$A$2:$A$11, MATCH(F110, PROVEEDORES!$B$2:$B$11, 0))) ,"")} -> PROV2 | M110: 3
A111: CONT110 | B111: El estado argentino: de los orígenes a la actualidad | F111: Ticmas | G111: {=IFERROR( IF(F111="","",INDEX(PROVEEDORES!$A$2:$A$11, MATCH(F111, PROVEEDORES!$B$2:$B$11, 0))) ,"")} -> PROV2 | M111: 4
A112: CONT111 | B112: ¿Por qué existen los problemas ambientales? A | F112: Ticmas | G112: {=IFERROR( IF(F112="","",INDEX(PROVEEDORES!$A$2:$A$11, MATCH(F112, PROVEEDORES!$B$2:$B$11, 0))) ,"")} -> PROV2 | M112: 3
A113: CONT112 | B113: ¿Por qué existen los problemas ambientales? B | F113: Ticmas | G113: {=IFERROR( IF(F113="","",INDEX(PROVEEDORES!$A$2:$A$11, MATCH(F113, PROVEEDORES!$B$2:$B$11, 0))) ,"")} -> PROV2 | M113: 4
A114: CONT113 | B114: Los circuitos productivos: del campo a la mesa A | F114: Ticmas | G114: {=IFERROR( IF(F114="","",INDEX(PROVEEDORES!$A$2:$A$11, MATCH(F114, PROVEEDORES!$B$2:$B$11, 0))) ,"")} -> PROV2 | M114: 3
A115: CONT114 | B115: Los circuitos productivos: del campo a la mesa B | F115: Ticmas | G115: {=IFERROR( IF(F115="","",INDEX(PROVEEDORES!$A$2:$A$11, MATCH(F115, PROVEEDORES!$B$2:$B$11, 0))) ,"")} -> PROV2 | M115: 4
A116: CONT115 | B116: Origenes del universo: Del universo a la célula A | F116: Ticmas | G116: {=IFERROR( IF(F116="","",INDEX(PROVEEDORES!$A$2:$A$11, MATCH(F116, PROVEEDORES!$B$2:$B$11, 0))) ,"")} -> PROV2 | H116: https://rise.articulate.com/share/2M5TtcEHZZS3_V82vJesJkEevY2Q-jzZ | M116: 1
A117: CONT116 | B117: Origenes del universo: Del universo a la célula B | F117: Ticmas | G117: {=IFERROR( IF(F117="","",INDEX(PROVEEDORES!$A$2:$A$11, MATCH(F117, PROVEEDORES!$B$2:$B$11, 0))) ,"")} -> PROV2 | H117: https://rise.articulate.com/share/v7zKvq9ucY48xJnk1qwbNkVRGtGv6PGB | M117: 2
A118: CONT117 | B118: El agua: de la naturaleza al laboratorio A | F118: Ticmas | G118: {=IFERROR( IF(F118="","",INDEX(PROVEEDORES!$A$2:$A$11, MATCH(F118, PROVEEDORES!$B$2:$B$11, 0))) ,"")} -> PROV2 | H118: https://rise.articulate.com/share/GyIVByQvlA8G5hQXP4Sw-L2H2yNgxyLS | M118: 1
A119: CONT118 | B119: El agua: de la naturaleza al laboratorio B | F119: Ticmas | G119: {=IFERROR( IF(F119="","",INDEX(PROVEEDORES!$A$2:$A$11, MATCH(F119, PROVEEDORES!$B$2:$B$11, 0))) ,"")} -> PROV2 | H119: https://rise.articulate.com/share/SzXNLbrL2cHwP7Ze1yzvu3r04qTbRNun | M119: 2
A120: CONT119 | B120: De la carreta al Maglev A | F120: Ticmas | G120: {=IFERROR( IF(F120="","",INDEX(PROVEEDORES!$A$2:$A$11, MATCH(F120, PROVEEDORES!$B$2:$B$11, 0))) ,"")} -> PROV2 | M120: 1
A121: CONT120 | B121: De la carreta al Maglev B | F121: Ticmas | G121: {=IFERROR( IF(F121="","",INDEX(PROVEEDORES!$A$2:$A$11, MATCH(F121, PROVEEDORES!$B$2:$B$11, 0))) ,"")} -> PROV2 | M121: 2
A122: CONT121 | B122: Descontaminación ambiental: de la Tierra al espacio A | F122: Ticmas | G122: {=IFERROR( IF(F122="","",INDEX(PROVEEDORES!$A$2:$A$11, MATCH(F122, PROVEEDORES!$B$2:$B$11, 0))) ,"")} -> PROV2 | H122: https://rise.articulate.com/share/DBSF-4B40fcESjJ6aCXMIvjo4bLlAAjt | M122: 1
A123: CONT122 | B123: Descontaminación ambiental: de la Tierra al espacio B | F123: Ticmas | G123: {=IFERROR( IF(F123="","",INDEX(PROVEEDORES!$A$2:$A$11, MATCH(F123, PROVEEDORES!$B$2:$B$11, 0))) ,"")} -> PROV2 | H123: https://rise.articulate.com/share/nnx75G3UuEOMI5QMhaldwpZrzNb_WuOF | M123: 2
A124: CONT123 | B124: Los descendientes de LUCA A | F124: Ticmas | G124: {=IFERROR( IF(F124="","",INDEX(PROVEEDORES!$A$2:$A$11, MATCH(F124, PROVEEDORES!$B$2:$B$11, 0))) ,"")} -> PROV2 | H124: https://rise.articulate.com/share/2MIxahV-8CA_IQOlOSF5m9HKoC4yXPNJ | M124: 1
A125: CONT124 | B125: Los descendientes de LUCA B | F125: Ticmas | G125: {=IFERROR( IF(F125="","",INDEX(PROVEEDORES!$A$2:$A$11, MATCH(F125, PROVEEDORES!$B$2:$B$11, 0))) ,"")} -> PROV2 | H125: https://rise.articulate.com/share/l2aJa1NnTthJdH-fa2eEdmxn_MaBey0Z | M125: 2
A126: CONT125 | B126: Ambiente, nutrición y salud reproductiva A | F126: Ticmas | G126: {=IFERROR( IF(F126="","",INDEX(PROVEEDORES!$A$2:$A$11, MATCH(F126, PROVEEDORES!$B$2:$B$11, 0))) ,"")} -> PROV2 | H126: https://rise.articulate.com/share/uY-k0swvqXITnhAr0Xoh7zYImQCXIaGU | M126: 3
A127: CONT126 | B127: Ambiente, nutrición y salud reproductiva B | F127: Ticmas | G127: {=IFERROR( IF(F127="","",INDEX(PROVEEDORES!$A$2:$A$11, MATCH(F127, PROVEEDORES!$B$2:$B$11, 0))) ,"")} -> PROV2 | M127: 4
A128: CONT127 | B128: ¿Una isla en la ciudad? A | F128: Ticmas | G128: {=IFERROR( IF(F128="","",INDEX(PROVEEDORES!$A$2:$A$11, MATCH(F128, PROVEEDORES!$B$2:$B$11, 0))) ,"")} -> PROV2 | M128: 3
A129: CONT128 | B129: ¿Una isla en la ciudad? B | F129: Ticmas | G129: {=IFERROR( IF(F129="","",INDEX(PROVEEDORES!$A$2:$A$11, MATCH(F129, PROVEEDORES!$B$2:$B$11, 0))) ,"")} -> PROV2 | M129: 4
A130: CONT129 | B130: Ciencia y ambiente para un futuro sostenible A | F130: Ticmas | G130: {=IFERROR( IF(F130="","",INDEX(PROVEEDORES!$A$2:$A$11, MATCH(F130, PROVEEDORES!$B$2:$B$11, 0))) ,"")} -> PROV2 | H130: https://rise.articulate.com/share/sOi0F9yvYoebE0Z6Buui_xtLBYjJcm-0 | M130: 3
A131: CONT130 | B131: Ciencia y ambiente para un futuro sostenible B | F131: Ticmas | G131: {=IFERROR( IF(F131="","",INDEX(PROVEEDORES!$A$2:$A$11, MATCH(F131, PROVEEDORES!$B$2:$B$11, 0))) ,"")} -> PROV2 | H131: https://rise.articulate.com/share/sOi0F9yvYoebE0Z6Buui_xtLBYjJcm-0 | M131: 4
A132: CONT131 | B132: Hormonas, neuronas y algo más en el deporte A | F132: Ticmas | G132: {=IFERROR( IF(F132="","",INDEX(PROVEEDORES!$A$2:$A$11, MATCH(F132, PROVEEDORES!$B$2:$B$11, 0))) ,"")} -> PROV2 | M132: 3
A133: CONT132 | B133: Hormonas, neuronas y algo más en el deporte B | F133: Ticmas | G133: {=IFERROR( IF(F133="","",INDEX(PROVEEDORES!$A$2:$A$11, MATCH(F133, PROVEEDORES!$B$2:$B$11, 0))) ,"")} -> PROV2 | M133: 4
A134: CONT133 | B134: Salud reproductiva y nutrición: un enfoque integral A | F134: Ticmas | G134: {=IFERROR( IF(F134="","",INDEX(PROVEEDORES!$A$2:$A$11, MATCH(F134, PROVEEDORES!$B$2:$B$11, 0))) ,"")} -> PROV2 | H134: https://rise.articulate.com/share/vu0-OFSIYdX6Wjzd3bNQpMizfC2gu8Qi | M134: 3
A135: CONT134 | B135: Salud reproductiva y nutrición: un enfoque integral B | F135: Ticmas | G135: {=IFERROR( IF(F135="","",INDEX(PROVEEDORES!$A$2:$A$11, MATCH(F135, PROVEEDORES!$B$2:$B$11, 0))) ,"")} -> PROV2 | H135: https://rise.articulate.com/share/LYH1yW4PZJ2GJLJu6x2ni8PkAlD3mXs9 | M135: 4
A136: CONT135 | B136: Conexiones en los sistemas neuroendocrinos A | F136: Ticmas | G136: {=IFERROR( IF(F136="","",INDEX(PROVEEDORES!$A$2:$A$11, MATCH(F136, PROVEEDORES!$B$2:$B$11, 0))) ,"")} -> PROV2 | M136: 3
A137: CONT136 | B137: Conexiones en los sistemas neuroendocrinos B | F137: Ticmas | G137: {=IFERROR( IF(F137="","",INDEX(PROVEEDORES!$A$2:$A$11, MATCH(F137, PROVEEDORES!$B$2:$B$11, 0))) ,"")} -> PROV2 | M137: 4
A138: CONT137 | B138: Genética y superpoderes A | F138: Ticmas | G138: {=IFERROR( IF(F138="","",INDEX(PROVEEDORES!$A$2:$A$11, MATCH(F138, PROVEEDORES!$B$2:$B$11, 0))) ,"")} -> PROV2 | H138: https://rise.articulate.com/share/ws-jKQzrN4ULnbuIWzigdsgmXYdPZOMZ | M138: 3
A139: CONT138 | B139: Genética y superpoderes B | F139: Ticmas | G139: {=IFERROR( IF(F139="","",INDEX(PROVEEDORES!$A$2:$A$11, MATCH(F139, PROVEEDORES!$B$2:$B$11, 0))) ,"")} -> PROV2 | M139: 4
A140: CONT139 | B140: La energía en nuestras casas A | F140: Ticmas | G140: {=IFERROR( IF(F140="","",INDEX(PROVEEDORES!$A$2:$A$11, MATCH(F140, PROVEEDORES!$B$2:$B$11, 0))) ,"")} -> PROV2 | M140: 3
A141: CONT140 | B141: La energía en nuestras casas B | F141: Ticmas | G141: {=IFERROR( IF(F141="","",INDEX(PROVEEDORES!$A$2:$A$11, MATCH(F141, PROVEEDORES!$B$2:$B$11, 0))) ,"")} -> PROV2 | M141: 4
A142: CONT141 | B142: Del ADN a tu plato A | F142: Ticmas | G142: {=IFERROR( IF(F142="","",INDEX(PROVEEDORES!$A$2:$A$11, MATCH(F142, PROVEEDORES!$B$2:$B$11, 0))) ,"")} -> PROV2 | M142: 3
A143: CONT142 | B143: Del ADN a tu plato B | F143: Ticmas | G143: {=IFERROR( IF(F143="","",INDEX(PROVEEDORES!$A$2:$A$11, MATCH(F143, PROVEEDORES!$B$2:$B$11, 0))) ,"")} -> PROV2 | M143: 4
A144: CONT143 | B144: Base de la gestión de proyectos BO | F144: Ticmas | G144: {=IFERROR( IF(F144="","",INDEX(PROVEEDORES!$A$2:$A$11, MATCH(F144, PROVEEDORES!$B$2:$B$11, 0))) ,"")} -> PROV2 | H144: https://rise.articulate.com/share/g0hPv0NhdLK9PJvl1ihdWFeMeKWZBRFl | M144: 1
A145: CONT144 | B145: Base de la gestión de proyectos Técnicas | F145: Ticmas | G145: {=IFERROR( IF(F145="","",INDEX(PROVEEDORES!$A$2:$A$11, MATCH(F145, PROVEEDORES!$B$2:$B$11, 0))) ,"")} -> PROV2 | M145: 1
A146: CONT145 | B146: El cuerpo y la actitud corporal | F146: Ticmas | G146: {=IFERROR( IF(F146="","",INDEX(PROVEEDORES!$A$2:$A$11, MATCH(F146, PROVEEDORES!$B$2:$B$11, 0))) ,"")} -> PROV2 | M146: 1
A147: CONT146 | B147: La acción, conflicto y desenlace | F147: Ticmas | G147: {=IFERROR( IF(F147="","",INDEX(PROVEEDORES!$A$2:$A$11, MATCH(F147, PROVEEDORES!$B$2:$B$11, 0))) ,"")} -> PROV2 | H147: https://rise.articulate.com/share/Ild47Yu_42bRn29SHwC3NpVXvw1XYEoj | M147: 2
A148: CONT147 | B148: Modelos, letras y música | F148: Ticmas | G148: {=IFERROR( IF(F148="","",INDEX(PROVEEDORES!$A$2:$A$11, MATCH(F148, PROVEEDORES!$B$2:$B$11, 0))) ,"")} -> PROV2 | M148: 3
A149: CONT148 | B149: Música: Características musicales | F149: Ticmas | G149: {=IFERROR( IF(F149="","",INDEX(PROVEEDORES!$A$2:$A$11, MATCH(F149, PROVEEDORES!$B$2:$B$11, 0))) ,"")} -> PROV2 | M149: 4
A150: CONT149 | B150: Fantasías, realismos y ficciones: Reproducción y matriz | F150: Ticmas | G150: {=IFERROR( IF(F150="","",INDEX(PROVEEDORES!$A$2:$A$11, MATCH(F150, PROVEEDORES!$B$2:$B$11, 0))) ,"")} -> PROV2 | M150: 1
A151: CONT150 | B151: Fantasías, realismos y ficciones: Arte moderno latinoamericano | F151: Ticmas | G151: {=IFERROR( IF(F151="","",INDEX(PROVEEDORES!$A$2:$A$11, MATCH(F151, PROVEEDORES!$B$2:$B$11, 0))) ,"")} -> PROV2 | H151: https://rise.articulate.com/share/aZgOJt8azD_Xz4Z96OCqz-I7L2n5clU8 | M151: 2
A152: CONT151 | B152: El territorio cotidiano: Conceptos claves | F152: Ticmas | G152: {=IFERROR( IF(F152="","",INDEX(PROVEEDORES!$A$2:$A$11, MATCH(F152, PROVEEDORES!$B$2:$B$11, 0))) ,"")} -> PROV2 | H152: https://rise.articulate.com/share/H0_h0-ADmdAxpTbafWk-qIoDk1e3T_zn | M152: 1
A153: CONT152 | B153: El territorio cotidiano: El objeto artístico | F153: Ticmas | G153: {=IFERROR( IF(F153="","",INDEX(PROVEEDORES!$A$2:$A$11, MATCH(F153, PROVEEDORES!$B$2:$B$11, 0))) ,"")} -> PROV2 | H153: https://rise.articulate.com/share/lAFjI6Cs2hjkqnOcWbJSIVJ_WHl8UF82 | M153: 3
A154: CONT153 | B154: La voz | F154: Ticmas | G154: {=IFERROR( IF(F154="","",INDEX(PROVEEDORES!$A$2:$A$11, MATCH(F154, PROVEEDORES!$B$2:$B$11, 0))) ,"")} -> PROV2 | M154: 4
A155: CONT154 | B155: El discurso | F155: Ticmas | G155: {=IFERROR( IF(F155="","",INDEX(PROVEEDORES!$A$2:$A$11, MATCH(F155, PROVEEDORES!$B$2:$B$11, 0))) ,"")} -> PROV2 | H155: https://rise.articulate.com/share/L6gPPXbXEe_60bYfOJmri1PePKTj_RXr | M155: 1
A156: CONT155 | B156: Teatro en todas partes | F156: Ticmas | G156: {=IFERROR( IF(F156="","",INDEX(PROVEEDORES!$A$2:$A$11, MATCH(F156, PROVEEDORES!$B$2:$B$11, 0))) ,"")} -> PROV2 | H156: https://rise.articulate.com/share/VuPgmyQVPSZzZtG_MdQGiXDpFyzORgUo | M156: 2
...

Sheet ESPACIO_CURRICULAR_SA
A1: ID_Espacio_curricular | B1: Codigo_Espacio_curricular | C1: Modalidad | D1: Modalidad_Tipo | E1: CantidadEspecialidades | F1: Año/Nivel | G1: Nombre_Espacio_curricular | H1: EsCompuesta | I1: Activo | J1: CategoriaPCI | K1: MateriasAgrupadas | L1: CategoriaFormacion
A2: ECURR1 | B2: SA-BACHI-CS-SOCIALES-Y-H-1-LENGUA-ADICIONAL-I | C2: SA | D2: Bachiller Común A | E2: 16 | F2: Nivel 1 | G2: Lengua Adicional I | H2: FALSE | I2: TRUE | J2: Troncal | K2: Lengua adicional | L2: Formación General
A3: ECURR2 | B3: SA-BACHI-CS-SOCIALES-Y-H-1-LENGUA-Y-LITERATURA- | C3: SA | D3: Bachiller Común A | E3: 16 | F3: Nivel 1 | G3: Lengua y Literatura I | H3: FALSE | I3: TRUE | J3: Troncal | K3: Lengua y Literatura | L3: Formación Orientada
A4: ECURR3 | B4: SA-BACHI-CS-SOCIALES-Y-H-1-MATEM-TICA-I | C4: SA | D4: Bachiller Común A | E4: 16 | F4: Nivel 1 | G4: Matemática I | H4: FALSE | I4: TRUE | J4: Troncal | K4: Matemáticas | L4: Formación General
A5: ECURR48 | B5: SA-BACHI-CS-SOCIALES-Y-H-1-LABORATORIO-CIENCIAS | C5: SA | D5: Bachiller Común A | E5: 16 | F5: Nivel 1 | G5: Laboratorio Ciencias Naturales A + B | H5: FALSE | I5: TRUE | J5: Laboratorio | K5: Biología | L5: Formación Orientada
A6: ECURR49 | B6: SA-BACHI-CS-SOCIALES-Y-H-1-LABORATORIO-CIENCIAS | C6: SA | D6: Bachiller Común A | E6: 16 | F6: Nivel 1 | G6: Laboratorio Ciencias Sociales A + B | H6: TRUE | I6: TRUE | J6: Laboratorio | K6: Historia; Geografía; Formación ética y ciudadana | L6: Formación General
A7: ECURR81 | B7: SA-BACHI-CS-SOCIALES-Y-H-1-TALLER-DE-ARTES-A-B | C7: SA | D7: Bachiller Común A | E7: 16 | F7: Nivel 1 | G7: Taller de Artes A + B | H7: TRUE | I7: TRUE | J7: Taller | K7: Artes; EDI; Tutoría | L7: Formación General
A8: ECURR82 | B8: SA-BACHI-CS-SOCIALES-Y-H-1-TALLER-DE-EDUCAIC-N- | C8: SA | D8: Bachiller Común A | E8: 16 | F8: Nivel 1 | G8: Taller de Educaicón Física A + B | H8: FALSE | I8: TRUE | J8: Taller | K8: Educación física | L8: Formación General
A9: ECURR83 | B9: SA-BACHI-CS-SOCIALES-Y-H-1-TALLER-DE-TECNOLOG-A | C9: SA | D9: Bachiller Común A | E9: 16 | F9: Nivel 1 | G9: Taller de Tecnología A | H9: FALSE | I9: TRUE | J9: Taller | K9: Educación tecnológica | L9: Formación General
A10: ECURR10 | B10: SA-BACHI-CS-SOCIALES-Y-H-2-LENGUA-ADICIONAL-II | C10: SA | D10: Bachiller Común A | E10: 16 | F10: Nivel 2 | G10: Lengua Adicional II | H10: FALSE | I10: TRUE | J10: Troncal | K10: Lengua adicional | L10: Formación General
A11: ECURR11 | B11: SA-BACHI-CS-SOCIALES-Y-H-2-LENGUA-Y-LITERATURA- | C11: SA | D11: Bachiller Común A | E11: 16 | F11: Nivel 2 | G11: Lengua y Literatura II | H11: FALSE | I11: TRUE | J11: Troncal | K11: Lengua y Literatura | L11: Formación Orientada
A12: ECURR12 | B12: SA-BACHI-CS-SOCIALES-Y-H-2-MATEM-TICA-II | C12: SA | D12: Bachiller Común A | E12: 16 | F12: Nivel 2 | G12: Matemática II | H12: FALSE | I12: TRUE | J12: Troncal | K12: Matemáticas | L12: Formación General
A13: ECURR54 | B13: SA-BACHI-CS-SOCIALES-Y-H-2-LABORATORIO-CIENCIAS | C13: SA | D13: Bachiller Común A | E13: 16 | F13: Nivel 2 | G13: Laboratorio Ciencias Naturales C + D | H13: FALSE | I13: TRUE | J13: Laboratorio | K13: Biología | L13: Formación Orientada
... A127: ECURR126 | B127: SA-TÉCNI-T-CNICO-MEC-NIC-6-PROYECTO-DE-EGRESO | C127: SA | D127: Técnica | E127: 11 | F127: Nivel 6 | G127: PROYECTO DE EGRESO | H127: FALSE | I127: TRUE | J127: Otro | K127: Prácticas profesionalizantes | L127: Formación General

Sheet TIPO_CONTENIDO
A1: TipoContenidoID | B1: Nombre | C1: Descripción | D1: Ícono | E1: Activo
A2: {=IF( B2:B2005 = "", "", "TCON" & ROW(B2:B2005) - 1 )} -> TCON1 | B2: Módulo | C2: Conjunto de recursos o clases organizadas en torno a un tema o competencia específica. Generalmente parte de un curso más amplio. | D2: 📘 | E2: TRUE
A3: TCON2 | B3: Módulo Interactivo | C3: Versión digital de un módulo, con navegación autónoma y elementos interactivos (Rise, Genially, H5P, etc.). | D3: 💡 | E3: TRUE
A4: TCON3 | B4: Juego educativo | C4: Actividad lúdica con reglas, objetivos y retroalimentación, diseñada para reforzar aprendizajes mediante la gamificación. | D4: 🎮 | E4: TRUE
A5: TCON4 | B5: Infografía interactiva | C5: Representación visual con elementos dinámicos o clicables que explican un concepto, proceso o conjunto de datos | D5: 🧭 | E5: TRUE
A6: TCON5 | B6: Microcontenido | C6: Recurso breve y puntual (video corto, ficha, cápsula o animación) que aborda un concepto específico o una habilidad puntual. | D6: ⚡ | E6: TRUE
A7: TCON6 | B7: Evaluación formativa | C7: Instrumento o actividad de evaluación con retroalimentación inmediata, orientada al seguimiento del aprendizaje (no calificativa). | D7: 🧩 | E7: TRUE
A8: TCON7 | B8: Contenido Curricular | C8: Material que desarrolla los saberes y objetivos prescriptos en el currículo oficial. Base para la planificación docente. | D8: 🗂️ | E8: TRUE
A9: TCON8 | B9: Secuencia Didáctica | C9: Conjunto de actividades planificadas que articulan objetivos, contenidos y estrategias de enseñanza y evaluación. | D9: 🧱 | E9: TRUE
A10: TCON9 | B10: Recurso Interactivo | C10: Material digital que requiere acción del usuario (clics, elecciones, arrastres, etc.) para explorar un contenido o resolver desafíos. | D10: 🖱️ | E10: TRUE
A11: TCON10 | B11: Video | C11: Recurso audiovisual lineal (grabación, animación o screencast) con propósito explicativo, motivacional o demostrativo. | D11: ▶️ | E11: TRUE
A12: TCON11 | B12: Texto | C12: Documento escrito que transmite información conceptual o narrativa (guía, artículo, ficha de lectura, ensayo, etc.). | D12: 📝 | E12: TRUE
A13: TCON12 | B13: Actividad Integradora | C13: Propuesta de trabajo que articula varios saberes o competencias en torno a un problema o proyecto común. | D13: 🔄 | E13: TRUE
A14: TCON13 | B14: Cuestionario | C14: Conjunto estructurado de preguntas cerradas o abiertas para comprobar la comprensión o recoger opiniones. | D14: ❓ | E14: TRUE
... A17: TCON16 | B17: Unidad | C17: Segmento curricular dentro de un curso, con objetivos, contenidos y actividades centrados en un tema específico. | D17: 📄 | E17: TRUE

Sheet ACTORES
A1: ActorID | B1: Nombre | C1: Apellido | D1: Apellidos y nombres | E1: Email | F1: Telefono_celular | G1: NúmeroInterno | H1: Rol | I1: Area_Ministerio | J1: TipoArea | K1: Número de puesto | L1: Activo
A2: {=IF( B2:B2006 = "", "", "ACT" & ROW(B2:B2006) - 1 )} | D2: =IF(OR(B2="",C2=""),"",C2&", "&B2) | H2: Programador/a | I2: GOICE - Gerencia Operativa de Innovación y Contenidos Educativos | J2: Gerencia Operativa | L2: TRUE
D3: =IF(OR(B3="",C3=""),"",C3&", "&B3) | H3: Admintrador/a | I3: GOED - Gerencia Operativa de Educación Digital | J3: Gerencia Operativa | L3: TRUE
D4: =IF(OR(B4="",C4=""),"",C4&", "&B4) | H4: Diseñador/a | I4: GOED - Gerencia Operativa de Educación Digital | J4: Gerencia Operativa | L4: TRUE
D5: =IF(OR(B5="",C5=""),"",C5&", "&B5) | H5: Analista Datos | I5: GOED - Gerencia Operativa de Educación Digital | J5: Gerencia Operativa | L5: TRUE
D6: =IF(OR(B6="",C6=""),"",C6&", "&B6) | L6: TRUE
D7: =IF(OR(B7="",C7=""),"",C7&", "&B7) | L7: TRUE
D8: =IF(OR(B8="",C8=""),"",C8&", "&B8) | L8: TRUE
D9: =IF(OR(B9="",C9=""),"",C9&", "&B9) | L9: TRUE
D10: =IF(OR(B10="",C10=""),"",C10&", "&B10) | L10: TRUE
D11: =IF(OR(B11="",C11=""),"",C11&", "&B11) | L11: TRUE
D12: =IF(OR(B12="",C12=""),"",C12&", "&B12) | L12: TRUE
D13: =IF(OR(B13="",C13=""),"",C13&", "&B13) | L13: TRUE
D14: =IF(OR(B14="",C14=""),"",C14&", "&B14) | L14: TRUE
D15: =IF(OR(B15="",C15=""),"",C15&", "&B15) | L15: TRUE
D16: =IF(OR(B16="",C16=""),"",C16&", "&B16) | L16: TRUE
D17: =IF(OR(B17="",C17=""),"",C17&", "&B17) | L17: TRUE
... D20: =IF(OR(B20="",C20=""),"",C20&", "&B20) | L20: TRUE

Sheet TIPO_PROVEEDOR
A1: TipoProveedorID | B1: Nombre | C1: Descripcion | D1: Activo
A2: 1 | B2: Externo | C2: Tipo 1 | D2: TRUE
A3: 2 | B3: Ministerio | C3: Tipo 2 | D3: TRUE
A4: 3 | B4: ONG | C4: Tipo 3 | D4: TRUE
A5: 4 | B5: Universidad | C5: Tipo 4 | D5: TRUE
A6: 5 | B6: Editorial | C6: Tipo 5 | D6: TRUE

Sheet PROVEEDORES
A1: ProveedorID | B1: Nombre_proveedor | C1: Nombre_tipo_proveedor | D1: TipoProveedorID | E1: Contacto | F1: Email | G1: Nombre_referente | H1: Especialidades | I1: Estado | J1: Descripcion | K1: Activo
A2: {=IF( B2:B1000 = "", "", "PROV" & ROW(B2:B1000) - 1 )} -> PROV1 | B2: Khan Academy | C2: Externo | E2: Team | F2: contact@khan.org | H2: Matemática | I2: ACTIVO | J2: Plataforma global | K2: TRUE
A3: PROV2 | B3: Ticmas | C3: Externo | E3: Contenidos | F3: info@ticmas.com | H3: Todas | I3: ACTIVO | J3: Plataforma AR | K3: TRUE
A4: PROV3 | B4: Editorial XYZ | E4: Comercial | F4: ventas@xyz.com | H4: Ciencias | I4: ACTIVO | J4: Editorial tradicional | K4: TRUE

Sheet MODALIDADES
A1: ModalidadID | B1: Nombre | C1: Descripcion | D1: Años_Duracion | E1: Sistema_Evaluacion | F1: Periodos_Año | G1: Activo
A2: BACH1 | B2: Bachiller Común A | C2: Desc 1 | D2: 5 | E2: Bimestre | F2: 4 | G2: TRUE
A3: BACH2 | B3: Bachiller Común B | C3: Desc 2 | D3: 5 | E3: Bimestre | F3: 4 | G3: TRUE
A4: TEC3 | B4: Técnica | C4: Desc 3 | D4: 6 | E4: Bimestre | F4: 4 | G4: TRUE

Sheet ESPECIALIDADES
A1: EspecialidadID | B1: ModalidadID | C1: Nombre | D1: Codigo | E1: Area | F1: Tipo | G1: Activo
A2: {=IF( B2:B2000 = "", "", "ESP" & ROW(B2:B2000) - 1 )} -> ESP1 | B2: BACH1 | C2: CS. SOCIALES Y HUMANIDADES (alternativa A) | D2: ESP-001 | E2: General | F2: SA/NES | G2: TRUE
A3: ESP2 | B3: BACH1 | C3: ARTES VISUALES (alternativa A) | D3: ESP-002 | E3: General | F3: SA/NES | G3: TRUE
A4: ESP3 | B4: BACH1 | C4: ARTE MUSICA (alternativa A) | D4: ESP-003 | E4: General | F4: SA/NES | G4: TRUE
A5: ESP4 | B5: BACH1 | C5: ARTE TEATRO (alternativa A) | D5: ESP-004 | E5: General | F5: SA/NES | G5: TRUE
A6: ESP5 | B6: BACH1 | C6: CS. NATURALES (alternativa A) | D6: ESP-005 | E6: General | F6: SA/NES | G6: TRUE
A7: ESP6 | B7: BACH1 | C7: COMUNICACIÓN (alternativa A) | D7: ESP-006 | E7: General | F7: SA/NES | G7: TRUE
A8: ESP7 | B8: BACH1 | C8: ECONOMÍA Y ADMINISTRACIÓN (alternativa A) | D8: ESP-007 | E8: General | F8: SA/NES | G8: TRUE
A9: ESP8 | B9: BACH1 | C9: EDUCACIÓN (alternativa A) | D9: ESP-008 | E9: General | F9: SA/NES | G9: TRUE
A10: ESP9 | B10: BACH1 | C10: EDUCACIÓN FÍSICA (alternativa A) | D10: ESP-009 | E10: General | F10: SA/NES | G10: TRUE
A11: ESP10 | B11: BACH1 | C11: ENERGÍA Y SUSTENTABILIDAD (alternativa A) | D11: ESP-010 | E11: General | F11: SA/NES | G11: TRUE
A12: ESP11 | B12: BACH1 | C12: INFORMÁTICA (alternativa A) | D12: ESP-011 | E12: General | F12: SA/NES | G12: TRUE
A13: ESP12 | B13: BACH1 | C13: LENGUAS (alternativa A) | D13: ESP-012 | E13: General | F13: SA/NES | G13: TRUE
A14: ESP13 | B14: BACH1 | C14: LITERATURA (alternativa A) | D14: ESP-013 | E14: General | F14: SA/NES | G14: TRUE
... A44: ESP43 | B44: TEC3 | C44: Técnico en QUÍMICA | D44: ESP-043 | E44: General | F44: SA/NES | G44: TRUE

Sheet AÑOS_ACADEMICOS
A1: AnioID | B1: Numero | C1: Nombre | D1: Ciclo | E1: Descripcion | F1: Activo
A2: 1 | B2: 1 | C2: Primer Año | D2: Ciclo Básico | E2: Año 1 | F2: TRUE
A3: 2 | B3: 2 | C3: Segundo Año | D3: Ciclo Básico | E3: Año 2 | F3: TRUE
A4: 3 | B4: 3 | C4: Tercer Año | D4: Ciclo Básico | E4: Año 3 | F4: TRUE
A5: 4 | B5: 4 | C5: Cuarto Año | D5: Ciclo Orientado | E5: Año 4 | F5: TRUE
A6: 5 | B6: 5 | C6: Quinto Año | D6: Ciclo Orientado | E6: Año 5 | F6: TRUE
A7: 6 | B7: 6 | C7: Sexto Año | D7: Ciclo Orientado | E7: Año 6 | F7: TRUE

Sheet PERIODOS_ACADEMICOS
A1: PeriodoID | B1: Nombre | C1: Tipo | D1: Duracion_Semanas | E1: Cantidad_Anual | F1: Descripcion | G1: Activo
A2: 1 | B2: Bimestre | C2: Bimestral | D2: 8 | E2: 4 | F2: Período bimestral | G2: TRUE
A3: 2 | B3: Cuatrimestre | C3: Cuatrimestre | D3: 16 | E3: 2 | F3: Período cuatrimestral

Sheet MATERIAS_UNIFICADAS
A1: IDMateria | B1: CodigoMateria | C1: Modalidad | D1: Modalidad_Tipo | E1: EspecialidadID | F1: Año/Nivel | G1: NombreMateria | H1: EsCompuesta | I1: Activo | J1: CategoriaPCI | K1: MateriasAgrupadas | L1: CategoriaFormacion
A2: 1 | B2: NES-BACHI-CS-SOCIALES-Y-H-1-MATEM-TICAS | C2: NES | D2: Bachiller Común A | E2: CS. SOCIALES Y HUMANIDADES | F2: 1 | G2: Matemáticas | H2: FALSE | I2: TRUE | L2: Formación General
A3: 2 | B3: SA-BACHI-CS-SOCIALES-Y-H-1-MATEM-TICA-I | C3: SA | D3: Bachiller Común A | E3: CS. SOCIALES Y HUMANIDADES | F3: Nivel 1 | G3: Matemática I | H3: FALSE | I3: TRUE | J3: Troncal | K3: Matemáticas | L3: Formación General
A4: 3 | B4: NES-BACHI-ARTES-VISUALES-1-MATEM-TICAS | C4: NES | D4: Bachiller Común A | E4: ARTES VISUALES | F4: 1 | G4: Matemáticas | H4: FALSE | I4: TRUE | L4: Formación General
A5: 4 | B5: SA-BACHI-ARTES-VISUALES-1-MATEM-TICA-I | C5: SA | D5: Bachiller Común A | E5: ARTES VISUALES | F5: Nivel 1 | G5: Matemática I | H5: FALSE | I5: TRUE | J5: Troncal | K5: Matemáticas | L5: Formación General
A6: 5 | B6: NES-BACHI-ARTE-MUSICA-1-MATEM-TICAS | C6: NES | D6: Bachiller Común A | E6: ARTE MUSICA | F6: 1 | G6: Matemáticas | H6: FALSE | I6: TRUE | L6: Formación General
A7: 6 | B7: SA-BACHI-ARTE-MUSICA-1-MATEM-TICA-I | C7: SA | D7: Bachiller Común A | E7: ARTE MUSICA | F7: Nivel 1 | G7: Matemática I | H7: FALSE | I7: TRUE | J7: Troncal | K7: Matemáticas | L7: Formación General
A8: 7 | B8: NES-BACHI-ARTE-TEATRO-1-MATEM-TICAS | C8: NES | D8: Bachiller Común A | E8: ARTE TEATRO | F8: 1 | G8: Matemáticas | H8: FALSE | I8: TRUE | L8: Formación General
A9: 8 | B9: SA-BACHI-ARTE-TEATRO-1-MATEM-TICA-I | C9: SA | D9: Bachiller Común A | E9: ARTE TEATRO | F9: Nivel 1 | G9: Matemática I | H9: FALSE | I9: TRUE | J9: Troncal | K9: Matemáticas | L9: Formación General
A10: 9 | B10: NES-BACHI-CS-NATURALES-1-MATEM-TICAS | C10: NES | D10: Bachiller Común A | E10: CS. NATURALES | F10: 1 | G10: Matemáticas | H10: FALSE | I10: TRUE | L10: Formación General
A11: 10 | B11: SA-BACHI-CS-NATURALES-1-MATEM-TICA-I | C11: SA | D11: Bachiller Común A | E11: CS. NATURALES | F11: Nivel 1 | G11: Matemática I | H11: FALSE | I11: TRUE | J11: Troncal | K11: Matemáticas | L11: Formación General
A12: 11 | B12: NES-BACHI-COMUNICACI-N-1-MATEM-TICAS | C12: NES | D12: Bachiller Común A | E12: COMUNICACIÓN | F12: 1 | G12: Matemáticas | H12: FALSE | I12: TRUE | L12: Formación General
A13: 12 | B13: SA-BACHI-COMUNICACI-N-1-MATEM-TICA-I | C13: SA | D13: Bachiller Común A | E13: COMUNICACIÓN | F13: Nivel 1 | G13: Matemática I | H13: FALSE | I13: TRUE | J13: Troncal | K13: Matemáticas | L13: Formación General
A14: 13 | B14: NES-BACHI-ECONOM-A-Y-ADMI-1-MATEM-TICAS | C14: NES | D14: Bachiller Común A | E14: ECONOMÍA Y ADMINISTRACIÓN | F14: 1 | G14: Matemáticas | H14: FALSE | I14: TRUE | L14: Formación General
A15: 14 | B15: SA-BACHI-ECONOM-A-Y-ADMI-1-MATEM-TICA-I | C15: SA | D15: Bachiller Común A | E15: ECONOMÍA Y ADMINISTRACIÓN | F15: Nivel 1 | G15: Matemática I | H15: FALSE | I15: TRUE | J15: Troncal | K15: Matemáticas | L15: Formación General
A16: 15 | B16: NES-BACHI-EDUCACI-N-1-MATEM-TICAS | C16: NES | D16: Bachiller Común A | E16: EDUCACIÓN | F16: 1 | G16: Matemáticas | H16: FALSE | I16: TRUE | L16: Formación General
A17: 16 | B17: SA-BACHI-EDUCACI-N-1-MATEM-TICA-I | C17: SA | D17: Bachiller Común A | E17: EDUCACIÓN | F17: Nivel 1 | G17: Matemática I | H17: FALSE | I17: TRUE | J17: Troncal | K17: Matemáticas | L17: Formación General
A18: 17 | B18: NES-BACHI-EDUCACI-N-F-SIC-1-MATEM-TICAS | C18: NES | D18: Bachiller Común A | E18: EDUCACIÓN FÍSICA | F18: 1 | G18: Matemáticas | H18: FALSE | I18: TRUE | L18: Formación General
A19: 18 | B19: SA-BACHI-EDUCACI-N-F-SIC-1-MATEM-TICA-I | C19: SA | D19: Bachiller Común A | E19: EDUCACIÓN FÍSICA | F19: Nivel 1 | G19: Matemática I | H19: FALSE | I19: TRUE | J19: Troncal | K19: Matemáticas | L19: Formación General
A20: 19 | B20: NES-BACHI-ENERG-A-Y-SUSTE-1-MATEM-TICAS | C20: NES | D20: Bachiller Común A | E20: ENERGÍA Y SUSTENTABILIDAD | F20: 1 | G20: Matemáticas | H20: FALSE | I20: TRUE | L20: Formación General
A21: 20 | B21: SA-BACHI-ENERG-A-Y-SUSTE-1-MATEM-TICA-I | C21: SA | D21: Bachiller Común A | E21: ENERGÍA Y SUSTENTABILIDAD | F21: Nivel 1 | G21: Matemática I | H21: FALSE | I21: TRUE | J21: Troncal | K21: Matemáticas | L21: Formación General
A22: 21 | B22: NES-BACHI-INFORM-TICA-1-MATEM-TICAS | C22: NES | D22: Bachiller Común A | E22: INFORMÁTICA | F22: 1 | G22: Matemáticas | H22: FALSE | I22: TRUE | L22: Formación General
A23: 22 | B23: SA-BACHI-INFORM-TICA-1-MATEM-TICA-I | C23: SA | D23: Bachiller Común A | E23: INFORMÁTICA | F23: Nivel 1 | G23: Matemática I | H23: FALSE | I23: TRUE | J23: Troncal | K23: Matemáticas | L23: Formación General
A24: 23 | B24: NES-BACHI-LENGUAS-1-MATEM-TICAS | C24: NES | D24: Bachiller Común A | E24: LENGUAS | F24: 1 | G24: Matemáticas | H24: FALSE | I24: TRUE | L24: Formación General
A25: 24 | B25: SA-BACHI-LENGUAS-1-MATEM-TICA-I | C25: SA | D25: Bachiller Común A | E25: LENGUAS | F25: Nivel 1 | G25: Matemática I | H25: FALSE | I25: TRUE | J25: Troncal | K25: Matemáticas | L25: Formación General
A26: 25 | B26: NES-BACHI-LITERATURA-1-MATEM-TICAS | C26: NES | D26: Bachiller Común A | E26: LITERATURA | F26: 1 | G26: Matemáticas | H26: FALSE | I26: TRUE | L26: Formación General
A27: 26 | B27: SA-BACHI-LITERATURA-1-MATEM-TICA-I | C27: SA | D27: Bachiller Común A | E27: LITERATURA | F27: Nivel 1 | G27: Matemática I | H27: FALSE | I27: TRUE | J27: Troncal | K27: Matemáticas | L27: Formación General
A28: 27 | B28: NES-BACHI-MATEM-TICA-Y-F--1-MATEM-TICAS | C28: NES | D28: Bachiller Común A | E28: MATEMÁTICA Y FÍSICA | F28: 1 | G28: Matemáticas | H28: FALSE | I28: TRUE | L28: Formación General
A29: 28 | B29: SA-BACHI-MATEM-TICA-Y-F--1-MATEM-TICA-I | C29: SA | D29: Bachiller Común A | E29: MATEMÁTICA Y FÍSICA | F29: Nivel 1 | G29: Matemática I | H29: FALSE | I29: TRUE | J29: Troncal | K29: Matemáticas | L29: Formación General
A30: 29 | B30: NES-BACHI-TURISMO-1-MATEM-TICAS | C30: NES | D30: Bachiller Común A | E30: TURISMO | F30: 1 | G30: Matemáticas | H30: FALSE | I30: TRUE | L30: Formación General
A31: 30 | B31: SA-BACHI-TURISMO-1-MATEM-TICA-I | C31: SA | D31: Bachiller Común A | E31: TURISMO | F31: Nivel 1 | G31: Matemática I | H31: FALSE | I31: TRUE | J31: Troncal | K31: Matemáticas | L31: Formación General
A32: 31 | B32: NES-BACHI-AGRO-Y-AMBIENTE-1-MATEM-TICAS | C32: NES | D32: Bachiller Común A | E32: AGRO Y AMBIENTE | F32: 1 | G32: Matemáticas | H32: FALSE | I32: TRUE | L32: Formación General
A33: 32 | B33: SA-BACHI-AGRO-Y-AMBIENTE-1-MATEM-TICA-I | C33: SA | D33: Bachiller Común A | E33: AGRO Y AMBIENTE | F33: Nivel 1 | G33: Matemática I | H33: FALSE | I33: TRUE | J33: Troncal | K33: Matemáticas | L33: Formación General
A34: 33 | B34: NES-BACHI-CS-SOCIALES-Y-H-1-LENGUA-Y-LITERATURA | C34: NES | D34: Bachiller Común A | E34: CS. SOCIALES Y HUMANIDADES | F34: 1 | G34: Lengua y Literatura | H34: FALSE | I34: TRUE | L34: Formación Orientada
A35: 34 | B35: SA-BACHI-CS-SOCIALES-Y-H-1-LENGUA-Y-LITERATURA- | C35: SA | D35: Bachiller Común A | E35: CS. SOCIALES Y HUMANIDADES | F35: Nivel 1 | G35: Lengua y Literatura I | H35: FALSE | I35: TRUE | J35: Troncal | K35: Lengua y Literatura | L35: Formación Orientada
A36: 35 | B36: NES-BACHI-ARTES-VISUALES-1-LENGUA-Y-LITERATURA | C36: NES | D36: Bachiller Común A | E36: ARTES VISUALES | F36: 1 | G36: Lengua y Literatura | H36: FALSE | I36: TRUE | L36: Formación Orientada
A37: 36 | B37: SA-BACHI-ARTES-VISUALES-1-LENGUA-Y-LITERATURA- | C37: SA | D37: Bachiller Común A | E37: ARTES VISUALES | F37: Nivel 1 | G37: Lengua y Literatura I | H37: FALSE | I37: TRUE | J37: Troncal | K37: Lengua y Literatura | L37: Formación Orientada
A38: 37 | B38: NES-BACHI-ARTE-MUSICA-1-LENGUA-Y-LITERATURA | C38: NES | D38: Bachiller Común A | E38: ARTE MUSICA | F38: 1 | G38: Lengua y Literatura | H38: FALSE | I38: TRUE | L38: Formación Orientada
A39: 38 | B39: SA-BACHI-ARTE-MUSICA-1-LENGUA-Y-LITERATURA- | C39: SA | D39: Bachiller Común A | E39: ARTE MUSICA | F39: Nivel 1 | G39: Lengua y Literatura I | H39: FALSE | I39: TRUE | J39: Troncal | K39: Lengua y Literatura | L39: Formación Orientada
A40: 39 | B40: NES-BACHI-ARTE-TEATRO-1-LENGUA-Y-LITERATURA | C40: NES | D40: Bachiller Común A | E40: ARTE TEATRO | F40: 1 | G40: Lengua y Literatura | H40: FALSE | I40: TRUE | L40: Formación Orientada
A41: 40 | B41: SA-BACHI-ARTE-TEATRO-1-LENGUA-Y-LITERATURA- | C41: SA | D41: Bachiller Común A | E41: ARTE TEATRO | F41: Nivel 1 | G41: Lengua y Literatura I | H41: FALSE | I41: TRUE | J41: Troncal | K41: Lengua y Literatura | L41: Formación Orientada
A42: 41 | B42: NES-BACHI-CS-NATURALES-1-LENGUA-Y-LITERATURA | C42: NES | D42: Bachiller Común A | E42: CS. NATURALES | F42: 1 | G42: Lengua y Literatura | H42: FALSE | I42: TRUE | L42: Formación Orientada
A43: 42 | B43: SA-BACHI-CS-NATURALES-1-LENGUA-Y-LITERATURA- | C43: SA | D43: Bachiller Común A | E43: CS. NATURALES | F43: Nivel 1 | G43: Lengua y Literatura I | H43: FALSE | I43: TRUE | J43: Troncal | K43: Lengua y Literatura | L43: Formación Orientada
A44: 43 | B44: NES-BACHI-COMUNICACI-N-1-LENGUA-Y-LITERATURA | C44: NES | D44: Bachiller Común A | E44: COMUNICACIÓN | F44: 1 | G44: Lengua y Literatura | H44: FALSE | I44: TRUE | L44: Formación Orientada
A45: 44 | B45: SA-BACHI-COMUNICACI-N-1-LENGUA-Y-LITERATURA- | C45: SA | D45: Bachiller Común A | E45: COMUNICACIÓN | F45: Nivel 1 | G45: Lengua y Literatura I | H45: FALSE | I45: TRUE | J45: Troncal | K45: Lengua y Literatura | L45: Formación Orientada
A46: 45 | B46: NES-BACHI-ECONOM-A-Y-ADMI-1-LENGUA-Y-LITERATURA | C46: NES | D46: Bachiller Común A | E46: ECONOMÍA Y ADMINISTRACIÓN | F46: 1 | G46: Lengua y Literatura | H46: FALSE | I46: TRUE | L46: Formación Orientada
A47: 46 | B47: SA-BACHI-ECONOM-A-Y-ADMI-1-LENGUA-Y-LITERATURA- | C47: SA | D47: Bachiller Común A | E47: ECONOMÍA Y ADMINISTRACIÓN | F47: Nivel 1 | G47: Lengua y Literatura I | H47: FALSE | I47: TRUE | J47: Troncal | K47: Lengua y Literatura | L47: Formación Orientada
A48: 47 | B48: NES-BACHI-EDUCACI-N-1-LENGUA-Y-LITERATURA | C48: NES | D48: Bachiller Común A | E48: EDUCACIÓN | F48: 1 | G48: Lengua y Literatura | H48: FALSE | I48: TRUE | L48: Formación Orientada
A49: 48 | B49: SA-BACHI-EDUCACI-N-1-LENGUA-Y-LITERATURA- | C49: SA | D49: Bachiller Común A | E49: EDUCACIÓN | F49: Nivel 1 | G49: Lengua y Literatura I | H49: FALSE | I49: TRUE | J49: Troncal | K49: Lengua y Literatura | L49: Formación Orientada
A50: 49 | B50: NES-BACHI-EDUCACI-N-F-SIC-1-LENGUA-Y-LITERATURA | C50: NES | D50: Bachiller Común A | E50: EDUCACIÓN FÍSICA | F50: 1 | G50: Lengua y Literatura | H50: FALSE | I50: TRUE | L50: Formación Orientada
A51: 50 | B51: SA-BACHI-EDUCACI-N-F-SIC-1-LENGUA-Y-LITERATURA- | C51: SA | D51: Bachiller Común A | E51: EDUCACIÓN FÍSICA | F51: Nivel 1 | G51: Lengua y Literatura I | H51: FALSE | I51: TRUE | J51: Troncal | K51: Lengua y Literatura | L51: Formación Orientada
A52: 51 | B52: NES-BACHI-ENERG-A-Y-SUSTE-1-LENGUA-Y-LITERATURA | C52: NES | D52: Bachiller Común A | E52: ENERGÍA Y SUSTENTABILIDAD | F52: 1 | G52: Lengua y Literatura | H52: FALSE | I52: TRUE | L52: Formación Orientada
A53: 52 | B53: SA-BACHI-ENERG-A-Y-SUSTE-1-LENGUA-Y-LITERATURA- | C53: SA | D53: Bachiller Común A | E53: ENERGÍA Y SUSTENTABILIDAD | F53: Nivel 1 | G53: Lengua y Literatura I | H53: FALSE | I53: TRUE | J53: Troncal | K53: Lengua y Literatura | L53: Formación Orientada
A54: 53 | B54: NES-BACHI-INFORM-TICA-1-LENGUA-Y-LITERATURA | C54: NES | D54: Bachiller Común A | E54: INFORMÁTICA | F54: 1 | G54: Lengua y Literatura | H54: FALSE | I54: TRUE | L54: Formación Orientada
A55: 54 | B55: SA-BACHI-INFORM-TICA-1-LENGUA-Y-LITERATURA- | C55: SA | D55: Bachiller Común A | E55: INFORMÁTICA | F55: Nivel 1 | G55: Lengua y Literatura I | H55: FALSE | I55: TRUE | J55: Troncal | K55: Lengua y Literatura | L55: Formación Orientada
A56: 55 | B56: NES-BACHI-LENGUAS-1-LENGUA-Y-LITERATURA | C56: NES | D56: Bachiller Común A | E56: LENGUAS | F56: 1 | G56: Lengua y Literatura | H56: FALSE | I56: TRUE | L56: Formación Orientada
A57: 56 | B57: SA-BACHI-LENGUAS-1-LENGUA-Y-LITERATURA- | C57: SA | D57: Bachiller Común A | E57: LENGUAS | F57: Nivel 1 | G57: Lengua y Literatura I | H57: FALSE | I57: TRUE | J57: Troncal | K57: Lengua y Literatura | L57: Formación Orientada
A58: 57 | B58: NES-BACHI-LITERATURA-1-LENGUA-Y-LITERATURA | C58: NES | D58: Bachiller Común A | E58: LITERATURA | F58: 1 | G58: Lengua y Literatura | H58: FALSE | I58: TRUE | L58: Formación Orientada
A59: 58 | B59: SA-BACHI-LITERATURA-1-LENGUA-Y-LITERATURA- | C59: SA | D59: Bachiller Común A | E59: LITERATURA | F59: Nivel 1 | G59: Lengua y Literatura I | H59: FALSE | I59: TRUE | J59: Troncal | K59: Lengua y Literatura | L59: Formación Orientada
A60: 59 | B60: NES-BACHI-MATEM-TICA-Y-F--1-LENGUA-Y-LITERATURA | C60: NES | D60: Bachiller Común A | E60: MATEMÁTICA Y FÍSICA | F60: 1 | G60: Lengua y Literatura | H60: FALSE | I60: TRUE | L60: Formación Orientada
A61: 60 | B61: SA-BACHI-MATEM-TICA-Y-F--1-LENGUA-Y-LITERATURA- | C61: SA | D61: Bachiller Común A | E61: MATEMÁTICA Y FÍSICA | F61: Nivel 1 | G61: Lengua y Literatura I | H61: FALSE | I61: TRUE | J61: Troncal | K61: Lengua y Literatura | L61: Formación Orientada
A62: 61 | B62: NES-BACHI-TURISMO-1-LENGUA-Y-LITERATURA | C62: NES | D62: Bachiller Común A | E62: TURISMO | F62: 1 | G62: Lengua y Literatura | H62: FALSE | I62: TRUE | L62: Formación Orientada
A63: 62 | B63: SA-BACHI-TURISMO-1-LENGUA-Y-LITERATURA- | C63: SA | D63: Bachiller Común A | E63: TURISMO | F63: Nivel 1 | G63: Lengua y Literatura I | H63: FALSE | I63: TRUE | J63: Troncal | K63: Lengua y Literatura | L63: Formación Orientada
A64: 63 | B64: NES-BACHI-AGRO-Y-AMBIENTE-1-LENGUA-Y-LITERATURA | C64: NES | D64: Bachiller Común A | E64: AGRO Y AMBIENTE | F64: 1 | G64: Lengua y Literatura | H64: FALSE | I64: TRUE | L64: Formación Orientada
A65: 64 | B65: SA-BACHI-AGRO-Y-AMBIENTE-1-LENGUA-Y-LITERATURA- | C65: SA | D65: Bachiller Común A | E65: AGRO Y AMBIENTE | F65: Nivel 1 | G65: Lengua y Literatura I | H65: FALSE | I65: TRUE | J65: Troncal | K65: Lengua y Literatura | L65: Formación Orientada
A66: 65 | B66: NES-BACHI-CS-SOCIALES-Y-H-1-LENGUA-ADICIONAL | C66: NES | D66: Bachiller Común A | E66: CS. SOCIALES Y HUMANIDADES | F66: 1 | G66: Lengua adicional | H66: FALSE | I66: TRUE | L66: Formación General
A67: 66 | B67: SA-BACHI-CS-SOCIALES-Y-H-1-LENGUA-ADICIONAL-I | C67: SA | D67: Bachiller Común A | E67: CS. SOCIALES Y HUMANIDADES | F67: Nivel 1 | G67: Lengua Adicional I | H67: FALSE | I67: TRUE | J67: Troncal | K67: Lengua adicional | L67: Formación General
A68: 67 | B68: NES-BACHI-ARTES-VISUALES-1-LENGUA-ADICIONAL | C68: NES | D68: Bachiller Común A | E68: ARTES VISUALES | F68: 1 | G68: Lengua adicional | H68: FALSE | I68: TRUE | L68: Formación General
A69: 68 | B69: SA-BACHI-ARTES-VISUALES-1-LENGUA-ADICIONAL-I | C69: SA | D69: Bachiller Común A | E69: ARTES VISUALES | F69: Nivel 1 | G69: Lengua Adicional I | H69: FALSE | I69: TRUE | J69: Troncal | K69: Lengua adicional | L69: Formación General
A70: 69 | B70: NES-BACHI-ARTE-MUSICA-1-LENGUA-ADICIONAL | C70: NES | D70: Bachiller Común A | E70: ARTE MUSICA | F70: 1 | G70: Lengua adicional | H70: FALSE | I70: TRUE | L70: Formación General
A71: 70 | B71: SA-BACHI-ARTE-MUSICA-1-LENGUA-ADICIONAL-I | C71: SA | D71: Bachiller Común A | E71: ARTE MUSICA | F71: Nivel 1 | G71: Lengua Adicional I | H71: FALSE | I71: TRUE | J71: Troncal | K71: Lengua adicional | L71: Formación General
A72: 71 | B72: NES-BACHI-ARTE-TEATRO-1-LENGUA-ADICIONAL | C72: NES | D72: Bachiller Común A | E72: ARTE TEATRO | F72: 1 | G72: Lengua adicional | H72: FALSE | I72: TRUE | L72: Formación General
A73: 72 | B73: SA-BACHI-ARTE-TEATRO-1-LENGUA-ADICIONAL-I | C73: SA | D73: Bachiller Común A | E73: ARTE TEATRO | F73: Nivel 1 | G73: Lengua Adicional I | H73: FALSE | I73: TRUE | J73: Troncal | K73: Lengua adicional | L73: Formación General
A74: 73 | B74: NES-BACHI-CS-NATURALES-1-LENGUA-ADICIONAL | C74: NES | D74: Bachiller Común A | E74: CS. NATURALES | F74: 1 | G74: Lengua adicional | H74: FALSE | I74: TRUE | L74: Formación General
A75: 74 | B75: SA-BACHI-CS-NATURALES-1-LENGUA-ADICIONAL-I | C75: SA | D75: Bachiller Común A | E75: CS. NATURALES | F75: Nivel 1 | G75: Lengua Adicional I | H75: FALSE | I75: TRUE | J75: Troncal | K75: Lengua adicional | L75: Formación General
A76: 75 | B76: NES-BACHI-COMUNICACI-N-1-LENGUA-ADICIONAL | C76: NES | D76: Bachiller Común A | E76: COMUNICACIÓN | F76: 1 | G76: Lengua adicional | H76: FALSE | I76: TRUE | L76: Formación General
A77: 76 | B77: SA-BACHI-COMUNICACI-N-1-LENGUA-ADICIONAL-I | C77: SA | D77: Bachiller Común A | E77: COMUNICACIÓN | F77: Nivel 1 | G77: Lengua Adicional I | H77: FALSE | I77: TRUE | J77: Troncal | K77: Lengua adicional | L77: Formación General
A78: 77 | B78: NES-BACHI-ECONOM-A-Y-ADMI-1-LENGUA-ADICIONAL | C78: NES | D78: Bachiller Común A | E78: ECONOMÍA Y ADMINISTRACIÓN | F78: 1 | G78: Lengua adicional | H78: FALSE | I78: TRUE | L78: Formación General
A79: 78 | B79: SA-BACHI-ECONOM-A-Y-ADMI-1-LENGUA-ADICIONAL-I | C79: SA | D79: Bachiller Común A | E79: ECONOMÍA Y ADMINISTRACIÓN | F79: Nivel 1 | G79: Lengua Adicional I | H79: FALSE | I79: TRUE | J79: Troncal | K79: Lengua adicional | L79: Formación General
A80: 79 | B80: NES-BACHI-EDUCACI-N-1-LENGUA-ADICIONAL | C80: NES | D80: Bachiller Común A | E80: EDUCACIÓN | F80: 1 | G80: Lengua adicional | H80: FALSE | I80: TRUE | L80: Formación General
A81: 80 | B81: SA-BACHI-EDUCACI-N-1-LENGUA-ADICIONAL-I | C81: SA | D81: Bachiller Común A | E81: EDUCACIÓN | F81: Nivel 1 | G81: Lengua Adicional I | H81: FALSE | I81: TRUE | J81: Troncal | K81: Lengua adicional | L81: Formación General
A82: 81 | B82: NES-BACHI-EDUCACI-N-F-SIC-1-LENGUA-ADICIONAL | C82: NES | D82: Bachiller Común A | E82: EDUCACIÓN FÍSICA | F82: 1 | G82: Lengua adicional | H82: FALSE | I82: TRUE | L82: Formación General
A83: 82 | B83: SA-BACHI-EDUCACI-N-F-SIC-1-LENGUA-ADICIONAL-I | C83: SA | D83: Bachiller Común A | E83: EDUCACIÓN FÍSICA | F83: Nivel 1 | G83: Lengua Adicional I | H83: FALSE | I83: TRUE | J83: Troncal | K83: Lengua adicional | L83: Formación General
A84: 83 | B84: NES-BACHI-ENERG-A-Y-SUSTE-1-LENGUA-ADICIONAL | C84: NES | D84: Bachiller Común A | E84: ENERGÍA Y SUSTENTABILIDAD | F84: 1 | G84: Lengua adicional | H84: FALSE | I84: TRUE | L84: Formación General
A85: 84 | B85: SA-BACHI-ENERG-A-Y-SUSTE-1-LENGUA-ADICIONAL-I | C85: SA | D85: Bachiller Común A | E85: ENERGÍA Y SUSTENTABILIDAD | F85: Nivel 1 | G85: Lengua Adicional I | H85: FALSE | I85: TRUE | J85: Troncal | K85: Lengua adicional | L85: Formación General
A86: 85 | B86: NES-BACHI-INFORM-TICA-1-LENGUA-ADICIONAL | C86: NES | D86: Bachiller Común A | E86: INFORMÁTICA | F86: 1 | G86: Lengua adicional | H86: FALSE | I86: TRUE | L86: Formación General
A87: 86 | B87: SA-BACHI-INFORM-TICA-1-LENGUA-ADICIONAL-I | C87: SA | D87: Bachiller Común A | E87: INFORMÁTICA | F87: Nivel 1 | G87: Lengua Adicional I | H87: FALSE | I87: TRUE | J87: Troncal | K87: Lengua adicional | L87: Formación General
A88: 87 | B88: NES-BACHI-LENGUAS-1-LENGUA-ADICIONAL | C88: NES | D88: Bachiller Común A | E88: LENGUAS | F88: 1 | G88: Lengua adicional | H88: FALSE | I88: TRUE | L88: Formación General
A89: 88 | B89: SA-BACHI-LENGUAS-1-LENGUA-ADICIONAL-I | C89: SA | D89: Bachiller Común A | E89: LENGUAS | F89: Nivel 1 | G89: Lengua Adicional I | H89: FALSE | I89: TRUE | J89: Troncal | K89: Lengua adicional | L89: Formación General
A90: 89 | B90: NES-BACHI-LITERATURA-1-LENGUA-ADICIONAL | C90: NES | D90: Bachiller Común A | E90: LITERATURA | F90: 1 | G90: Lengua adicional | H90: FALSE | I90: TRUE | L90: Formación General
A91: 90 | B91: SA-BACHI-LITERATURA-1-LENGUA-ADICIONAL-I | C91: SA | D91: Bachiller Común A | E91: LITERATURA | F91: Nivel 1 | G91: Lengua Adicional I | H91: FALSE | I91: TRUE | J91: Troncal | K91: Lengua adicional | L91: Formación General
A92: 91 | B92: NES-BACHI-MATEM-TICA-Y-F--1-LENGUA-ADICIONAL | C92: NES | D92: Bachiller Común A | E92: MATEMÁTICA Y FÍSICA | F92: 1 | G92: Lengua adicional | H92: FALSE | I92: TRUE | L92: Formación General
A93: 92 | B93: SA-BACHI-MATEM-TICA-Y-F--1-LENGUA-ADICIONAL-I | C93: SA | D93: Bachiller Común A | E93: MATEMÁTICA Y FÍSICA | F93: Nivel 1 | G93: Lengua Adicional I | H93: FALSE | I93: TRUE | J93: Troncal | K93: Lengua adicional | L93: Formación General
A94: 93 | B94: NES-BACHI-TURISMO-1-LENGUA-ADICIONAL | C94: NES | D94: Bachiller Común A | E94: TURISMO | F94: 1 | G94: Lengua adicional | H94: FALSE | I94: TRUE | L94: Formación General
A95: 94 | B95: SA-BACHI-TURISMO-1-LENGUA-ADICIONAL-I | C95: SA | D95: Bachiller Común A | E95: TURISMO | F95: Nivel 1 | G95: Lengua Adicional I | H95: FALSE | I95: TRUE | J95: Troncal | K95: Lengua adicional | L95: Formación General
A96: 95 | B96: NES-BACHI-AGRO-Y-AMBIENTE-1-LENGUA-ADICIONAL | C96: NES | D96: Bachiller Común A | E96: AGRO Y AMBIENTE | F96: 1 | G96: Lengua adicional | H96: FALSE | I96: TRUE | L96: Formación General
A97: 96 | B97: SA-BACHI-AGRO-Y-AMBIENTE-1-LENGUA-ADICIONAL-I | C97: SA | D97: Bachiller Común A | E97: AGRO Y AMBIENTE | F97: Nivel 1 | G97: Lengua Adicional I | H97: FALSE | I97: TRUE | J97: Troncal | K97: Lengua adicional | L97: Formación General
A98: 97 | B98: NES-BACHI-CS-SOCIALES-Y-H-1-BIOLOG-A | C98: NES | D98: Bachiller Común A | E98: CS. SOCIALES Y HUMANIDADES | F98: 1 | G98: Biología | H98: FALSE | I98: TRUE | L98: Formación General
A99: 98 | B99: SA-BACHI-CS-SOCIALES-Y-H-1-LABORATORIO-CIENCIAS | C99: SA | D99: Bachiller Común A | E99: CS. SOCIALES Y HUMANIDADES | F99: Nivel 1 | G99: Laboratorio Ciencias Naturales A + B | H99: FALSE | I99: TRUE | J99: Laboratorio | K99: Biología | L99: Formación Orientada
A100: 99 | B100: NES-BACHI-ARTES-VISUALES-1-BIOLOG-A | C100: NES | D100: Bachiller Común A | E100: ARTES VISUALES | F100: 1 | G100: Biología | H100: FALSE | I100: TRUE | L100: Formación General
...

Sheet Contenidos_SA_mapeados_GOICE
A1: Contenido_ID | B1: ÁREAS | C1: ESPACIO CURRICULAR | D1: Nivel | E1: Bimestre | F1: Tipo de cursada | G1: TÍTULO DEL PLAN | H1: Enlaces | I1: Columna 9 | J1: Nivel_num | K1: MateriasSA | L1: CategoriaPCI | M1: CategoriaFormacion | N1: Modalidad_Tipo | O1: Especialidades | P1: EsCompuesta | Q1: MateriasNES_Agrupadas | R1: ContenidosPriorizadosID
A2: 1 | B2: Matemática | C2: Matemática | D2: 1 | E2: 1 | F2: Obligatorio | G2: Números naturales y números enteros | J2: 1 | K2: Mat Nivel 1 | Matemática I | L2: Troncal | M2: Formación General | N2: Bachiller Común A | Bachiller Común B | Técnica | O2: AGRO Y AMBIENTE | ARTE MUSICA | ARTE TEATRO | ARTES VISUALES | COMUNICACIÓN | CS. NATURALES | CS. SOCIALES Y HUMANIDADES | ECONOMÍA Y ADMINISTRACIÓN | EDUCACIÓN | EDUCACIÓN FÍSICA | ENERGÍA Y SUSTENTABILIDAD | INFORMÁTICA | LENGUAS | LITERATURA | MATEMÁTICA Y FÍSICA | TURISMO | Técnico AUTOMOTORES | Técnico ELECTRICISTA | Técnico MECÁNICO | Técnico MECÁNICO ELECTRICISTA | P2: Sí | Q2: Matemáticas
A3: 2 | B3: Matemática | C3: Matemática | D3: 1 | E3: 2 | F3: Obligatorio | G3: Gráficos cartesianos | J3: 1 | K3: Mat Nivel 1 | Matemática I | L3: Troncal | M3: Formación General | N3: Bachiller Común A | Bachiller Común B | Técnica | O3: AGRO Y AMBIENTE | ARTE MUSICA | ARTE TEATRO | ARTES VISUALES | COMUNICACIÓN | CS. NATURALES | CS. SOCIALES Y HUMANIDADES | ECONOMÍA Y ADMINISTRACIÓN | EDUCACIÓN | EDUCACIÓN FÍSICA | ENERGÍA Y SUSTENTABILIDAD | INFORMÁTICA | LENGUAS | LITERATURA | MATEMÁTICA Y FÍSICA | TURISMO | Técnico AUTOMOTORES | Técnico ELECTRICISTA | Técnico MECÁNICO | Técnico MECÁNICO ELECTRICISTA | P3: Sí | Q3: Matemáticas
A4: 3 | B4: Matemática | C4: Matemática | D4: 1 | E4: 3 | F4: Obligatorio | G4: Triángulos | J4: 1 | K4: Mat Nivel 1 | Matemática I | L4: Troncal | M4: Formación General | N4: Bachiller Común A | Bachiller Común B | Técnica | O4: AGRO Y AMBIENTE | ARTE MUSICA | ARTE TEATRO | ARTES VISUALES | COMUNICACIÓN | CS. NATURALES | CS. SOCIALES Y HUMANIDADES | ECONOMÍA Y ADMINISTRACIÓN | EDUCACIÓN | EDUCACIÓN FÍSICA | ENERGÍA Y SUSTENTABILIDAD | INFORMÁTICA | LENGUAS | LITERATURA | MATEMÁTICA Y FÍSICA | TURISMO | Técnico AUTOMOTORES | Técnico ELECTRICISTA | Técnico MECÁNICO | Técnico MECÁNICO ELECTRICISTA | P4: Sí | Q4: Matemáticas
A5: 4 | B5: Matemática | C5: Matemática | D5: 1 | E5: 4 | F5: Obligatorio | G5: Estadística | J5: 1 | K5: Mat Nivel 1 | Matemática I | L5: Troncal | M5: Formación General | N5: Bachiller Común A | Bachiller Común B | Técnica | O5: AGRO Y AMBIENTE | ARTE MUSICA | ARTE TEATRO | ARTES VISUALES | COMUNICACIÓN | CS. NATURALES | CS. SOCIALES Y HUMANIDADES | ECONOMÍA Y ADMINISTRACIÓN | EDUCACIÓN | EDUCACIÓN FÍSICA | ENERGÍA Y SUSTENTABILIDAD | INFORMÁTICA | LENGUAS | LITERATURA | MATEMÁTICA Y FÍSICA | TURISMO | Técnico AUTOMOTORES | Técnico ELECTRICISTA | Técnico MECÁNICO | Técnico MECÁNICO ELECTRICISTA | P5: Sí | Q5: Matemáticas
A6: 5 | B6: Matemática | C6: Matemática | D6: 2 | E6: 1 | F6: Obligatorio | G6: Divisibilidad | J6: 2 | K6: Mat Nivel 2 | Matemática II | L6: Troncal | M6: Formación General | N6: Bachiller Común A | Bachiller Común B | Técnica | O6: AGRO Y AMBIENTE | ARTE MUSICA | ARTE TEATRO | ARTES VISUALES | COMUNICACIÓN | CS. NATURALES | CS. SOCIALES Y HUMANIDADES | ECONOMÍA Y ADMINISTRACIÓN | EDUCACIÓN | EDUCACIÓN FÍSICA | ENERGÍA Y SUSTENTABILIDAD | INFORMÁTICA | LENGUAS | LITERATURA | MATEMÁTICA Y FÍSICA | TURISMO | Técnico AUTOMOTORES | Técnico ELECTRICISTA | Técnico MECÁNICO | Técnico MECÁNICO ELECTRICISTA | P6: Sí | Q6: Matemáticas
A7: 6 | B7: Matemática | C7: Matemática | D7: 2 | E7: 2 | F7: Obligatorio | G7: Función lineal | J7: 2 | K7: Mat Nivel 2 | Matemática II | L7: Troncal | M7: Formación General | N7: Bachiller Común A | Bachiller Común B | Técnica | O7: AGRO Y AMBIENTE | ARTE MUSICA | ARTE TEATRO | ARTES VISUALES | COMUNICACIÓN | CS. NATURALES | CS. SOCIALES Y HUMANIDADES | ECONOMÍA Y ADMINISTRACIÓN | EDUCACIÓN | EDUCACIÓN FÍSICA | ENERGÍA Y SUSTENTABILIDAD | INFORMÁTICA | LENGUAS | LITERATURA | MATEMÁTICA Y FÍSICA | TURISMO | Técnico AUTOMOTORES | Técnico ELECTRICISTA | Técnico MECÁNICO | Técnico MECÁNICO ELECTRICISTA | P7: Sí | Q7: Matemáticas
A8: 7 | B8: Matemática | C8: Matemática | D8: 2 | E8: 3 | F8: Obligatorio | G8: Cuadriláteros y Teorema de Thales | J8: 2 | K8: Mat Nivel 2 | Matemática II | L8: Troncal | M8: Formación General | N8: Bachiller Común A | Bachiller Común B | Técnica | O8: AGRO Y AMBIENTE | ARTE MUSICA | ARTE TEATRO | ARTES VISUALES | COMUNICACIÓN | CS. NATURALES | CS. SOCIALES Y HUMANIDADES | ECONOMÍA Y ADMINISTRACIÓN | EDUCACIÓN | EDUCACIÓN FÍSICA | ENERGÍA Y SUSTENTABILIDAD | INFORMÁTICA | LENGUAS | LITERATURA | MATEMÁTICA Y FÍSICA | TURISMO | Técnico AUTOMOTORES | Técnico ELECTRICISTA | Técnico MECÁNICO | Técnico MECÁNICO ELECTRICISTA | P8: Sí | Q8: Matemáticas
A9: 8 | B9: Matemática | C9: Matemática | D9: 2 | E9: 4 | F9: Obligatorio | G9: Estadística | J9: 2 | K9: Mat Nivel 2 | Matemática II | L9: Troncal | M9: Formación General | N9: Bachiller Común A | Bachiller Común B | Técnica | O9: AGRO Y AMBIENTE | ARTE MUSICA | ARTE TEATRO | ARTES VISUALES | COMUNICACIÓN | CS. NATURALES | CS. SOCIALES Y HUMANIDADES | ECONOMÍA Y ADMINISTRACIÓN | EDUCACIÓN | EDUCACIÓN FÍSICA | ENERGÍA Y SUSTENTABILIDAD | INFORMÁTICA | LENGUAS | LITERATURA | MATEMÁTICA Y FÍSICA | TURISMO | Técnico AUTOMOTORES | Técnico ELECTRICISTA | Técnico MECÁNICO | Técnico MECÁNICO ELECTRICISTA | P9: Sí | Q9: Matemáticas
A10: 9 | B10: Matemática | C10: Matemática | D10: 3 | E10: 1 | F10: Obligatorio | G10: Problemas de conteo | J10: 3 | K10: Mat Nivel 3 | Matemática III | Taller de la Especialidad | L10: Troncal | M10: Formación General | N10: Bachiller Común A | Bachiller Común B | Técnica | O10: AGRO Y AMBIENTE | ARTE MUSICA | ARTE TEATRO | ARTES VISUALES | COMUNICACIÓN | CS. NATURALES | CS. SOCIALES Y HUMANIDADES | ECONOMÍA Y ADMINISTRACIÓN | EDUCACIÓN | EDUCACIÓN FÍSICA | ENERGÍA Y SUSTENTABILIDAD | INFORMÁTICA | LENGUAS | LITERATURA | MATEMÁTICA Y FÍSICA | TURISMO | Técnico AUTOMOTORES | Técnico ELECTRICISTA | Técnico MECÁNICO | Técnico MECÁNICO ELECTRICISTA | P10: Sí | Q10: Matemática || Matemáticas || Taller de Tecnología y Control; Taller de Geografía Matemática
A11: 10 | B11: Matemática | C11: Matemática | D11: 3 | E11: 2 | F11: Obligatorio | G11: Sistema de ecuaciones | J11: 3 | K11: Mat Nivel 3 | Matemática III | Taller de la Especialidad | L11: Troncal | M11: Formación General | N11: Bachiller Común A | Bachiller Común B | Técnica | O11: AGRO Y AMBIENTE | ARTE MUSICA | ARTE TEATRO | ARTES VISUALES | COMUNICACIÓN | CS. NATURALES | CS. SOCIALES Y HUMANIDADES | ECONOMÍA Y ADMINISTRACIÓN | EDUCACIÓN | EDUCACIÓN FÍSICA | ENERGÍA Y SUSTENTABILIDAD | INFORMÁTICA | LENGUAS | LITERATURA | MATEMÁTICA Y FÍSICA | TURISMO | Técnico AUTOMOTORES | Técnico ELECTRICISTA | Técnico MECÁNICO | Técnico MECÁNICO ELECTRICISTA | P11: Sí | Q11: Matemática || Matemáticas || Taller de Tecnología y Control; Taller de Geografía Matemática
A12: 11 | B12: Matemática | C12: Matemática | D12: 3 | E12: 3 | F12: Obligatorio | G12: Razones trigonométricas | J12: 3 | K12: Mat Nivel 3 | Matemática III | Taller de la Especialidad | L12: Troncal | M12: Formación General | N12: Bachiller Común A | Bachiller Común B | Técnica | O12: AGRO Y AMBIENTE | ARTE MUSICA | ARTE TEATRO | ARTES VISUALES | COMUNICACIÓN | CS. NATURALES | CS. SOCIALES Y HUMANIDADES | ECONOMÍA Y ADMINISTRACIÓN | EDUCACIÓN | EDUCACIÓN FÍSICA | ENERGÍA Y SUSTENTABILIDAD | INFORMÁTICA | LENGUAS | LITERATURA | MATEMÁTICA Y FÍSICA | TURISMO | Técnico AUTOMOTORES | Técnico ELECTRICISTA | Técnico MECÁNICO | Técnico MECÁNICO ELECTRICISTA | P12: Sí | Q12: Matemática || Matemáticas || Taller de Tecnología y Control; Taller de Geografía Matemática
A13: 12 | B13: Matemática | C13: Matemática | D13: 3 | E13: 4 | F13: Obligatorio | G13: Función cuadrática | J13: 3 | K13: Mat Nivel 3 | Matemática III | Taller de la Especialidad | L13: Troncal | M13: Formación General | N13: Bachiller Común A | Bachiller Común B | Técnica | O13: AGRO Y AMBIENTE | ARTE MUSICA | ARTE TEATRO | ARTES VISUALES | COMUNICACIÓN | CS. NATURALES | CS. SOCIALES Y HUMANIDADES | ECONOMÍA Y ADMINISTRACIÓN | EDUCACIÓN | EDUCACIÓN FÍSICA | ENERGÍA Y SUSTENTABILIDAD | INFORMÁTICA | LENGUAS | LITERATURA | MATEMÁTICA Y FÍSICA | TURISMO | Técnico AUTOMOTORES | Técnico ELECTRICISTA | Técnico MECÁNICO | Técnico MECÁNICO ELECTRICISTA | P13: Sí | Q13: Matemática || Matemáticas || Taller de Tecnología y Control; Taller de Geografía Matemática
... A143: 142 | B143: Ciencias Naturales | C143: Cs. naturales | D143: 5 | E143: 4 | F143: Electivo | G143: Del ADN a tu plato B | J143: 5 | K143: Laboratorio Ciencias Naturales I | L143: Laboratorio | M143: Formación Orientada | N143: Bachiller Común A | Bachiller Común B | O143: AGRO Y AMBIENTE | ARTE MUSICA | ARTE TEATRO | ARTES VISUALES | COMUNICACIÓN | CS. NATURALES | CS. SOCIALES Y HUMANIDADES | ECONOMÍA Y ADMINISTRACIÓN | EDUCACIÓN | EDUCACIÓN FÍSICA | ENERGÍA Y SUSTENTABILIDAD | INFORMÁTICA | LENGUAS | LITERATURA | MATEMÁTICA Y FÍSICA | TURISMO | P143: Sí | Q143: Química
A144: 143 | B144: Proyecto | C144: Plan Bimestral_ Bases de la Gestión de Proyectos.docx | D144: 45813 | E144: 1 | F144: Obligatorio | G144: Base de la gestión de proyectos BO | L144: Troncal
A145: 144 | B145: Proyecto | C145: Plan Bimestral_ Bases de la Gestión de Proyectos - TÉCNICAS.docx | D145: 6 | E145: 1 | F145: Obligatorio | G145: Base de la gestión de proyectos Técnicas | J145: 6 | L145: Troncal
A146: 145 | B146: Arte | C146: Artes | D146: 1 | E146: 1 | F146: Electivo | G146: El cuerpo y la actitud corporal | J146: 1 | K146: Taller de Artes A + B | L146: Taller | M146: Formación General | N146: Bachiller Común A | Bachiller Común B | O146: AGRO Y AMBIENTE | ARTE MUSICA | ARTE TEATRO | ARTES VISUALES | COMUNICACIÓN | CS. NATURALES | CS. SOCIALES Y HUMANIDADES | ECONOMÍA Y ADMINISTRACIÓN | EDUCACIÓN | EDUCACIÓN FÍSICA | ENERGÍA Y SUSTENTABILIDAD | INFORMÁTICA | LENGUAS | LITERATURA | MATEMÁTICA Y FÍSICA | TURISMO | P146: Sí | Q146: Artes; EDI; Tutoría
A147: 146 | B147: Arte | C147: Artes | D147: 1 | E147: 2 | F147: Electivo | G147: La acción, conflicto y desenlace | J147: 1 | K147: Taller de Artes A + B | L147: Taller | M147: Formación General | N147: Bachiller Común A | Bachiller Común B | O147: AGRO Y AMBIENTE | ARTE MUSICA | ARTE TEATRO | ARTES VISUALES | COMUNICACIÓN | CS. NATURALES | CS. SOCIALES Y HUMANIDADES | ECONOMÍA Y ADMINISTRACIÓN | EDUCACIÓN | EDUCACIÓN FÍSICA | ENERGÍA Y SUSTENTABILIDAD | INFORMÁTICA | LENGUAS | LITERATURA | MATEMÁTICA Y FÍSICA | TURISMO | P147: Sí | Q147: Artes; EDI; Tutoría
A148: 147 | B148: Arte | C148: Artes | D148: 1 | E148: 3 | F148: Electivo | G148: Modelos, letras y música | J148: 1 | K148: Taller de Artes A + B | L148: Taller | M148: Formación General | N148: Bachiller Común A | Bachiller Común B | O148: AGRO Y AMBIENTE | ARTE MUSICA | ARTE TEATRO | ARTES VISUALES | COMUNICACIÓN | CS. NATURALES | CS. SOCIALES Y HUMANIDADES | ECONOMÍA Y ADMINISTRACIÓN | EDUCACIÓN | EDUCACIÓN FÍSICA | ENERGÍA Y SUSTENTABILIDAD | INFORMÁTICA | LENGUAS | LITERATURA | MATEMÁTICA Y FÍSICA | TURISMO | P148: Sí | Q148: Artes; EDI; Tutoría
A149: 148 | B149: Arte | C149: Artes | D149: 1 | E149: 4 | F149: Electivo | G149: Música: Características musicales | J149: 1 | K149: Taller de Artes A + B | L149: Taller | M149: Formación General | N149: Bachiller Común A | Bachiller Común B | O149: AGRO Y AMBIENTE | ARTE MUSICA | ARTE TEATRO | ARTES VISUALES | COMUNICACIÓN | CS. NATURALES | CS. SOCIALES Y HUMANIDADES | ECONOMÍA Y ADMINISTRACIÓN | EDUCACIÓN | EDUCACIÓN FÍSICA | ENERGÍA Y SUSTENTABILIDAD | INFORMÁTICA | LENGUAS | LITERATURA | MATEMÁTICA Y FÍSICA | TURISMO | P149: Sí | Q149: Artes; EDI; Tutoría
A150: 149 | B150: Arte | C150: Artes | D150: 2 | E150: 1 | F150: Electivo | G150: Quién es quién: Fantasías, realismos y ficciones: Reproducción y matriz | J150: 2 | K150: Taller de Artes C + D | L150: Taller | M150: Formación General | N150: Bachiller Común A | Bachiller Común B | O150: AGRO Y AMBIENTE | ARTE MUSICA | ARTE TEATRO | ARTES VISUALES | COMUNICACIÓN | CS. NATURALES | CS. SOCIALES Y HUMANIDADES | ECONOMÍA Y ADMINISTRACIÓN | EDUCACIÓN | EDUCACIÓN FÍSICA | ENERGÍA Y SUSTENTABILIDAD | INFORMÁTICA | LENGUAS | LITERATURA | MATEMÁTICA Y FÍSICA | TURISMO | P150: Sí | Q150: Artes; EDI; Tutoría
A151: 150 | B151: Arte | C151: Artes | D151: 2 | E151: 2 | F151: Electivo | G151: Quién es quién: Fantasías, realismos y ficciones: Arte moderno latinoamericano | J151: 2 | K151: Taller de Artes C + D | L151: Taller | M151: Formación General | N151: Bachiller Común A | Bachiller Común B | O151: AGRO Y AMBIENTE | ARTE MUSICA | ARTE TEATRO | ARTES VISUALES | COMUNICACIÓN | CS. NATURALES | CS. SOCIALES Y HUMANIDADES | ECONOMÍA Y ADMINISTRACIÓN | EDUCACIÓN | EDUCACIÓN FÍSICA | ENERGÍA Y SUSTENTABILIDAD | INFORMÁTICA | LENGUAS | LITERATURA | MATEMÁTICA Y FÍSICA | TURISMO | P151: Sí | Q151: Artes; EDI; Tutoría
A152: 151 | B152: Arte | C152: Artes | D152: 2 | E152: 1 | F152: Electivo | G152: El territorio cotidiano: Conceptos claves | J152: 2 | K152: Taller de Artes C + D | L152: Taller | M152: Formación General | N152: Bachiller Común A | Bachiller Común B | O152: AGRO Y AMBIENTE | ARTE MUSICA | ARTE TEATRO | ARTES VISUALES | COMUNICACIÓN | CS. NATURALES | CS. SOCIALES Y HUMANIDADES | ECONOMÍA Y ADMINISTRACIÓN | EDUCACIÓN | EDUCACIÓN FÍSICA | ENERGÍA Y SUSTENTABILIDAD | INFORMÁTICA | LENGUAS | LITERATURA | MATEMÁTICA Y FÍSICA | TURISMO | P152: Sí | Q152: Artes; EDI; Tutoría
A153: 152 | B153: Arte | C153: Artes | D153: 2 | E153: 3 | F153: Electivo | G153: El territorio cotidiano: El objeto como obra de arte | J153: 2 | K153: Taller de Artes C + D | L153: Taller | M153: Formación General | N153: Bachiller Común A | Bachiller Común B | O153: AGRO Y AMBIENTE | ARTE MUSICA | ARTE TEATRO | ARTES VISUALES | COMUNICACIÓN | CS. NATURALES | CS. SOCIALES Y HUMANIDADES | ECONOMÍA Y ADMINISTRACIÓN | EDUCACIÓN | EDUCACIÓN FÍSICA | ENERGÍA Y SUSTENTABILIDAD | INFORMÁTICA | LENGUAS | LITERATURA | MATEMÁTICA Y FÍSICA | TURISMO | P153: Sí | Q153: Artes; EDI; Tutoría
A154: 153 | B154: Arte | C154: Artes | D154: 2 | E154: 4 | F154: Electivo | G154: Música: La voz | J154: 2 | K154: Taller de Artes C + D | L154: Taller | M154: Formación General | N154: Bachiller Común A | Bachiller Común B | O154: AGRO Y AMBIENTE | ARTE MUSICA | ARTE TEATRO | ARTES VISUALES | COMUNICACIÓN | CS. NATURALES | CS. SOCIALES Y HUMANIDADES | ECONOMÍA Y ADMINISTRACIÓN | EDUCACIÓN | EDUCACIÓN FÍSICA | ENERGÍA Y SUSTENTABILIDAD | INFORMÁTICA | LENGUAS | LITERATURA | MATEMÁTICA Y FÍSICA | TURISMO | P154: Sí | Q154: Artes; EDI; Tutoría
A155: 154 | B155: Arte | C155: Artes | D155: 3 | E155: 1 | F155: Electivo | G155: El discurso | J155: 3 | K155: Laboratorio de la Orientación A + Taller de la Orientación A | L155: Taller | M155: Formación Orientada | N155: Bachiller Común A | Bachiller Común B | O155: ARTES VISUALES | LITERATURA | P155: Sí | Q155: Taller de Producción en Lenguajes: Literatura y otras Artes; EDI || Taller de artes visuales; EDI
A156: 155 | B156: Arte | C156: Artes | D156: 3 | E156: 2 | F156: Electivo | G156: Teatro en todas partes | J156: 3 | K156: Laboratorio de la Orientación A + Taller de la Orientación A | L156: Taller | M156: Formación Orientada | N156: Bachiller Común A | Bachiller Común B | O156: ARTES VISUALES | LITERATURA | P156: Sí | Q156: Taller de Producción en Lenguajes: Literatura y otras Artes; EDI || Taller de artes visuales; EDI
A157: 156 | B157: Arte | C157: Artes | D157: 3 | E157: 3 | F157: Electivo | G157: Música y artes visuales: Ocupando el espacio sonoro | J157: 3 | K157: Laboratorio de la Orientación A + Taller de la Orientación A | L157: Taller | M157: Formación Orientada | N157: Bachiller Común A | Bachiller Común B | O157: ARTES VISUALES | LITERATURA | P157: Sí | Q157: Taller de Producción en Lenguajes: Literatura y otras Artes; EDI || Taller de artes visuales; EDI
... A179: 178 | B179: Arte | C179: Arte y tecnología | D179: 3 | E179: 1 | F179: Electivo | G179: Reflexión, crítica y autonomía con IA | J179: 3 | K179: Taller de Tecnología C + D | Taller de la Especialidad | L179: Taller | M179: Formación General | N179: Bachiller Común A | Bachiller Común B | Técnica | O179: AGRO Y AMBIENTE | ARTE MUSICA | ARTE TEATRO | ARTES VISUALES | COMUNICACIÓN | CS. NATURALES | CS. SOCIALES Y HUMANIDADES | ECONOMÍA Y ADMINISTRACIÓN | EDUCACIÓN | EDUCACIÓN FÍSICA | ENERGÍA Y SUSTENTABILIDAD | INFORMÁTICA | LENGUAS | LITERATURA | MATEMÁTICA Y FÍSICA | TURISMO | Técnico AUTOMOTORES | Técnico ELECTRICISTA | Técnico MECÁNICO | Técnico MECÁNICO ELECTRICISTA | P179: Sí | Q179: Taller de Tecnología y Control; --Taller || Taller de Tecnología y Control; Taller de Geografía Matemática || Taller tecnología y del control; Taller de la especialidad || Tecnologías de la información
A180: 179 | B180: Educación física | C180: Educ. Física | D180: 1 | E180: 1 | G180: Prácticas introyectivas (yoga) | J180: 1 | K180: Laboratorio Ciencias Naturales A + B | L180: Laboratorio | M180: Formación Orientada | N180: Bachiller Común A | Bachiller Común B | O180: AGRO Y AMBIENTE | ARTE MUSICA | ARTE TEATRO | ARTES VISUALES | COMUNICACIÓN | CS. NATURALES | CS. SOCIALES Y HUMANIDADES | ECONOMÍA Y ADMINISTRACIÓN | EDUCACIÓN | EDUCACIÓN FÍSICA | ENERGÍA Y SUSTENTABILIDAD | INFORMÁTICA | LENGUAS | LITERATURA | MATEMÁTICA Y FÍSICA | TURISMO | P180: Sí | Q180: Biología
A181: 180 | B181: Educación física | C181: Educ. Física | D181: 1 | E181: 2 | G181: Expresión y ritmo | J181: 1 | K181: Laboratorio Ciencias Naturales A + B | L181: Laboratorio | M181: Formación Orientada | N181: Bachiller Común A | Bachiller Común B | O181: AGRO Y AMBIENTE | ARTE MUSICA | ARTE TEATRO | ARTES VISUALES | COMUNICACIÓN | CS. NATURALES | CS. SOCIALES Y HUMANIDADES | ECONOMÍA Y ADMINISTRACIÓN | EDUCACIÓN | EDUCACIÓN FÍSICA | ENERGÍA Y SUSTENTABILIDAD | INFORMÁTICA | LENGUAS | LITERATURA | MATEMÁTICA Y FÍSICA | TURISMO | P181: Sí | Q181: Biología
A182: 181 | B182: Educación física | C182: Educ. Física | D182: 1 | E182: 3 | G182: Gimnasia artística | J182: 1 | K182: Laboratorio Ciencias Naturales A + B | L182: Laboratorio | M182: Formación Orientada | N182: Bachiller Común A | Bachiller Común B | O182: AGRO Y AMBIENTE | ARTE MUSICA | ARTE TEATRO | ARTES VISUALES | COMUNICACIÓN | CS. NATURALES | CS. SOCIALES Y HUMANIDADES | ECONOMÍA Y ADMINISTRACIÓN | EDUCACIÓN | EDUCACIÓN FÍSICA | ENERGÍA Y SUSTENTABILIDAD | INFORMÁTICA | LENGUAS | LITERATURA | MATEMÁTICA Y FÍSICA | TURISMO | P182: Sí | Q182: Biología
A183: 182 | B183: Educación física | C183: Educ. Física | D183: 1 | E183: 4 | G183: Salto con soga | J183: 1 | K183: Laboratorio Ciencias Naturales A + B | L183: Laboratorio | M183: Formación Orientada | N183: Bachiller Común A | Bachiller Común B | O183: AGRO Y AMBIENTE | ARTE MUSICA | ARTE TEATRO | ARTES VISUALES | COMUNICACIÓN | CS. NATURALES | CS. SOCIALES Y HUMANIDADES | ECONOMÍA Y ADMINISTRACIÓN | EDUCACIÓN | EDUCACIÓN FÍSICA | ENERGÍA Y SUSTENTABILIDAD | INFORMÁTICA | LENGUAS | LITERATURA | MATEMÁTICA Y FÍSICA | TURISMO | P183: Sí | Q183: Biología
A184: 183 | B184: Educación física | C184: Educ. Física | D184: 1 | E184: 4 | G184: Prácticas circenses | J184: 1 | K184: Laboratorio Ciencias Naturales A + B | L184: Laboratorio | M184: Formación Orientada | N184: Bachiller Común A | Bachiller Común B | O184: AGRO Y AMBIENTE | ARTE MUSICA | ARTE TEATRO | ARTES VISUALES | COMUNICACIÓN | CS. NATURALES | CS. SOCIALES Y HUMANIDADES | ECONOMÍA Y ADMINISTRACIÓN | EDUCACIÓN | EDUCACIÓN FÍSICA | ENERGÍA Y SUSTENTABILIDAD | INFORMÁTICA | LENGUAS | LITERATURA | MATEMÁTICA Y FÍSICA | TURISMO | P184: Sí | Q184: Biología
A185: 184 | B185: Educación física | C185: Educ. Física | D185: 2 | E185: 1 | G185: Juegos y deportes alternativos: ringo | J185: 2 | K185: Laboratorio Ciencias Naturales C + D | L185: Laboratorio | M185: Formación Orientada | N185: Bachiller Común A | Bachiller Común B | O185: AGRO Y AMBIENTE | ARTE MUSICA | ARTE TEATRO | ARTES VISUALES | COMUNICACIÓN | CS. NATURALES | CS. SOCIALES Y HUMANIDADES | ECONOMÍA Y ADMINISTRACIÓN | EDUCACIÓN | EDUCACIÓN FÍSICA | ENERGÍA Y SUSTENTABILIDAD | INFORMÁTICA | LENGUAS | LITERATURA | MATEMÁTICA Y FÍSICA | TURISMO | P185: Sí | Q185: Biología
A186: 185 | B186: Educación física | C186: Educ. Física | D186: 2 | E186: 2 | G186: Juegos y deportes alternativos: Parkour | J186: 2 | K186: Laboratorio Ciencias Naturales C + D | L186: Laboratorio | M186: Formación Orientada | N186: Bachiller Común A | Bachiller Común B | O186: AGRO Y AMBIENTE | ARTE MUSICA | ARTE TEATRO | ARTES VISUALES | COMUNICACIÓN | CS. NATURALES | CS. SOCIALES Y HUMANIDADES | ECONOMÍA Y ADMINISTRACIÓN | EDUCACIÓN | EDUCACIÓN FÍSICA | ENERGÍA Y SUSTENTABILIDAD | INFORMÁTICA | LENGUAS | LITERATURA | MATEMÁTICA Y FÍSICA | TURISMO | P186: Sí | Q186: Biología
A187: 186 | B187: Educación física | C187: Educ. Física | D187: 2 | E187: 3 | G187: Fútbol 1 | J187: 2 | K187: Laboratorio Ciencias Naturales C + D | L187: Laboratorio | M187: Formación Orientada | N187: Bachiller Común A | Bachiller Común B | O187: AGRO Y AMBIENTE | ARTE MUSICA | ARTE TEATRO | ARTES VISUALES | COMUNICACIÓN | CS. NATURALES | CS. SOCIALES Y HUMANIDADES | ECONOMÍA Y ADMINISTRACIÓN | EDUCACIÓN | EDUCACIÓN FÍSICA | ENERGÍA Y SUSTENTABILIDAD | INFORMÁTICA | LENGUAS | LITERATURA | MATEMÁTICA Y FÍSICA | TURISMO | P187: Sí | Q187: Biología
A188: 187 | B188: Educación física | C188: Educ. Física | D188: 2 | E188: 4 | G188: La caminata: una experiencia motriz saludable | J188: 2 | K188: Laboratorio Ciencias Naturales C + D | L188: Laboratorio | M188: Formación Orientada | N188: Bachiller Común A | Bachiller Común B | O188: AGRO Y AMBIENTE | ARTE MUSICA | ARTE TEATRO | ARTES VISUALES | COMUNICACIÓN | CS. NATURALES | CS. SOCIALES Y HUMANIDADES | ECONOMÍA Y ADMINISTRACIÓN | EDUCACIÓN | EDUCACIÓN FÍSICA | ENERGÍA Y SUSTENTABILIDAD | INFORMÁTICA | LENGUAS | LITERATURA | MATEMÁTICA Y FÍSICA | TURISMO | P188: Sí | Q188: Biología
A189: 188 | B189: Educación física | C189: Educ. Física | D189: 2 | E189: 4 | G189: Atletismo 1 | J189: 2 | K189: Laboratorio Ciencias Naturales C + D | L189: Laboratorio | M189: Formación Orientada | N189: Bachiller Común A | Bachiller Común B | O189: AGRO Y AMBIENTE | ARTE MUSICA | ARTE TEATRO | ARTES VISUALES | COMUNICACIÓN | CS. NATURALES | CS. SOCIALES Y HUMANIDADES | ECONOMÍA Y ADMINISTRACIÓN | EDUCACIÓN | EDUCACIÓN FÍSICA | ENERGÍA Y SUSTENTABILIDAD | INFORMÁTICA | LENGUAS | LITERATURA | MATEMÁTICA Y FÍSICA | TURISMO | P189: Sí | Q189: Biología
A190: 189 | B190: Educación física | C190: Educ. Física | D190: 3 | E190: 1 | G190: De la observación a la acción: aprender en la naturaleza | J190: 3 | K190: Laboratorio Ciencias Naturales E + F | L190: Laboratorio | M190: Formación Orientada | N190: Bachiller Común A | Bachiller Común B | O190: AGRO Y AMBIENTE | ARTE MUSICA | ARTE TEATRO | ARTES VISUALES | COMUNICACIÓN | CS. NATURALES | CS. SOCIALES Y HUMANIDADES | ECONOMÍA Y ADMINISTRACIÓN | EDUCACIÓN | EDUCACIÓN FÍSICA | ENERGÍA Y SUSTENTABILIDAD | INFORMÁTICA | LENGUAS | LITERATURA | MATEMÁTICA Y FÍSICA | TURISMO | P190: Sí | Q190: Biología; Fisico-química
A191: 190 | B191: Educación física | C191: Educ. Física | D191: 3 | E191: 2 | G191: Handball 1 | J191: 3 | K191: Laboratorio Ciencias Naturales E + F | L191: Laboratorio | M191: Formación Orientada | N191: Bachiller Común A | Bachiller Común B | O191: AGRO Y AMBIENTE | ARTE MUSICA | ARTE TEATRO | ARTES VISUALES | COMUNICACIÓN | CS. NATURALES | CS. SOCIALES Y HUMANIDADES | ECONOMÍA Y ADMINISTRACIÓN | EDUCACIÓN | EDUCACIÓN FÍSICA | ENERGÍA Y SUSTENTABILIDAD | INFORMÁTICA | LENGUAS | LITERATURA | MATEMÁTICA Y FÍSICA | TURISMO | P191: Sí | Q191: Biología; Fisico-química
... A203: 202 | B203: Educación física | C203: Educ. Física | D203: 5 | E203: 4 | G203: Bádminton | J203: 5 | K203: Laboratorio Ciencias Naturales I | L203: Laboratorio | M203: Formación Orientada | N203: Bachiller Común A | Bachiller Común B | O203: AGRO Y AMBIENTE | ARTE MUSICA | ARTE TEATRO | ARTES VISUALES | COMUNICACIÓN | CS. NATURALES | CS. SOCIALES Y HUMANIDADES | ECONOMÍA Y ADMINISTRACIÓN | EDUCACIÓN | EDUCACIÓN FÍSICA | ENERGÍA Y SUSTENTABILIDAD | INFORMÁTICA | LENGUAS | LITERATURA | MATEMÁTICA Y FÍSICA | TURISMO | P203: Sí | Q203: Química
A204: 203 | B204: BACHILLERATO ORIENTADO | C204: Arte - Teatro | D204: 4 | E204: 1 | F204: Laboratorios | G204: Transformaciones en el espacio escénico A | J204: 4 | K204: Laboratorio de la Orientación B + Taller de la Orientación B | Taller de Artes G + H | L204: Taller | M204: Formación General | Formación Orientada | N204: Bachiller Común A | Bachiller Común B | O204: AGRO Y AMBIENTE | ARTE MUSICA | ARTE TEATRO | ARTES VISUALES | COMUNICACIÓN | CS. NATURALES | CS. SOCIALES Y HUMANIDADES | ECONOMÍA Y ADMINISTRACIÓN | EDUCACIÓN | EDUCACIÓN FÍSICA | ENERGÍA Y SUSTENTABILIDAD | INFORMÁTICA | LENGUAS | LITERATURA | MATEMÁTICA Y FÍSICA | TURISMO | P204: Sí | Q204: Artes || Taller de artes visuales; Artes en contextos históricos; Lenguajes artísticos combinados; EDI || Taller de música; Artes en contextos históricos; Lenguajes artísticos combinados; EDI || Taller de teatro; Artes en contextos históricos; Lenguajes artísticos combinado; EDI
A205: 204 | B205: BACHILLERATO ORIENTADO | C205: Arte - Teatro | D205: 4 | E205: 2 | F205: Laboratorios | G205: Transformaciones en el espacio escénico B | J205: 4 | K205: Laboratorio de la Orientación B + Taller de la Orientación B | Taller de Artes G + H | L205: Taller | M205: Formación General | Formación Orientada | N205: Bachiller Común A | Bachiller Común B | O205: AGRO Y AMBIENTE | ARTE MUSICA | ARTE TEATRO | ARTES VISUALES | COMUNICACIÓN | CS. NATURALES | CS. SOCIALES Y HUMANIDADES | ECONOMÍA Y ADMINISTRACIÓN | EDUCACIÓN | EDUCACIÓN FÍSICA | ENERGÍA Y SUSTENTABILIDAD | INFORMÁTICA | LENGUAS | LITERATURA | MATEMÁTICA Y FÍSICA | TURISMO | P205: Sí | Q205: Artes || Taller de artes visuales; Artes en contextos históricos; Lenguajes artísticos combinados; EDI || Taller de música; Artes en contextos históricos; Lenguajes artísticos combinados; EDI || Taller de teatro; Artes en contextos históricos; Lenguajes artísticos combinado; EDI
A206: 205 | B206: BACHILLERATO ORIENTADO | C206: Arte - Teatro | D206: 4 | E206: 1 | F206: Laboratorios | G206: Circuitos teatrales en Buenos Aires | J206: 4 | K206: Laboratorio de la Orientación B + Taller de la Orientación B | Taller de Artes G + H | L206: Taller | M206: Formación General | Formación Orientada | N206: Bachiller Común A | Bachiller Común B | O206: AGRO Y AMBIENTE | ARTE MUSICA | ARTE TEATRO | ARTES VISUALES | COMUNICACIÓN | CS. NATURALES | CS. SOCIALES Y HUMANIDADES | ECONOMÍA Y ADMINISTRACIÓN | EDUCACIÓN | EDUCACIÓN FÍSICA | ENERGÍA Y SUSTENTABILIDAD | INFORMÁTICA | LENGUAS | LITERATURA | MATEMÁTICA Y FÍSICA | TURISMO | P206: Sí | Q206: Artes || Taller de artes visuales; Artes en contextos históricos; Lenguajes artísticos combinados; EDI || Taller de música; Artes en contextos históricos; Lenguajes artísticos combinados; EDI || Taller de teatro; Artes en contextos históricos; Lenguajes artísticos combinado; EDI
A207: 206 | B207: BACHILLERATO ORIENTADO | C207: Arte - Teatro | D207: 4 | E207: 2 | F207: Laboratorios | G207: Creación y producción: del oficio a la escena multimedial | J207: 4 | K207: Laboratorio de la Orientación B + Taller de la Orientación B | Taller de Artes G + H | L207: Taller | M207: Formación General | Formación Orientada | N207: Bachiller Común A | Bachiller Común B | O207: AGRO Y AMBIENTE | ARTE MUSICA | ARTE TEATRO | ARTES VISUALES | COMUNICACIÓN | CS. NATURALES | CS. SOCIALES Y HUMANIDADES | ECONOMÍA Y ADMINISTRACIÓN | EDUCACIÓN | EDUCACIÓN FÍSICA | ENERGÍA Y SUSTENTABILIDAD | INFORMÁTICA | LENGUAS | LITERATURA | MATEMÁTICA Y FÍSICA | TURISMO | P207: Sí | Q207: Artes || Taller de artes visuales; Artes en contextos históricos; Lenguajes artísticos combinados; EDI || Taller de música; Artes en contextos históricos; Lenguajes artísticos combinados; EDI || Taller de teatro; Artes en contextos históricos; Lenguajes artísticos combinado; EDI
A208: 207 | B208: BACHILLERATO ORIENTADO | C208: Arte - Teatro | D208: 4 | E208: 1 | F208: Laboratorios | G208: Raíces e influencias en la identidad cultural | J208: 4 | K208: Laboratorio de la Orientación B + Taller de la Orientación B | Taller de Artes G + H | L208: Taller | M208: Formación General | Formación Orientada | N208: Bachiller Común A | Bachiller Común B | O208: AGRO Y AMBIENTE | ARTE MUSICA | ARTE TEATRO | ARTES VISUALES | COMUNICACIÓN | CS. NATURALES | CS. SOCIALES Y HUMANIDADES | ECONOMÍA Y ADMINISTRACIÓN | EDUCACIÓN | EDUCACIÓN FÍSICA | ENERGÍA Y SUSTENTABILIDAD | INFORMÁTICA | LENGUAS | LITERATURA | MATEMÁTICA Y FÍSICA | TURISMO | P208: Sí | Q208: Artes || Taller de artes visuales; Artes en contextos históricos; Lenguajes artísticos combinados; EDI || Taller de música; Artes en contextos históricos; Lenguajes artísticos combinados; EDI || Taller de teatro; Artes en contextos históricos; Lenguajes artísticos combinado; EDI
A209: 208 | B209: BACHILLERATO ORIENTADO | C209: Arte - Teatro | D209: 4 | E209: 2 | F209: Laboratorios | G209: Innovación, tecnología y participación en el teatro | J209: 4 | K209: Laboratorio de la Orientación B + Taller de la Orientación B | Taller de Artes G + H | L209: Taller | M209: Formación General | Formación Orientada | N209: Bachiller Común A | Bachiller Común B | O209: AGRO Y AMBIENTE | ARTE MUSICA | ARTE TEATRO | ARTES VISUALES | COMUNICACIÓN | CS. NATURALES | CS. SOCIALES Y HUMANIDADES | ECONOMÍA Y ADMINISTRACIÓN | EDUCACIÓN | EDUCACIÓN FÍSICA | ENERGÍA Y SUSTENTABILIDAD | INFORMÁTICA | LENGUAS | LITERATURA | MATEMÁTICA Y FÍSICA | TURISMO | P209: Sí | Q209: Artes || Taller de artes visuales; Artes en contextos históricos; Lenguajes artísticos combinados; EDI || Taller de música; Artes en contextos históricos; Lenguajes artísticos combinados; EDI || Taller de teatro; Artes en contextos históricos; Lenguajes artísticos combinado; EDI
A210: 209 | B210: BACHILLERATO ORIENTADO | C210: Arte - Teatro | D210: 4 | E210: 3 | F210: Talleres | G210: Teatro Clown: el arte de la risa y la vulnerabilidad A | J210: 4 | K210: Laboratorio de la Orientación B + Taller de la Orientación B | Taller de Artes G + H | L210: Taller | M210: Formación General | Formación Orientada | N210: Bachiller Común A | Bachiller Común B | O210: AGRO Y AMBIENTE | ARTE MUSICA | ARTE TEATRO | ARTES VISUALES | COMUNICACIÓN | CS. NATURALES | CS. SOCIALES Y HUMANIDADES | ECONOMÍA Y ADMINISTRACIÓN | EDUCACIÓN | EDUCACIÓN FÍSICA | ENERGÍA Y SUSTENTABILIDAD | INFORMÁTICA | LENGUAS | LITERATURA | MATEMÁTICA Y FÍSICA | TURISMO | P210: Sí | Q210: Artes || Taller de artes visuales; Artes en contextos históricos; Lenguajes artísticos combinados; EDI || Taller de música; Artes en contextos históricos; Lenguajes artísticos combinados; EDI || Taller de teatro; Artes en contextos históricos; Lenguajes artísticos combinado; EDI
A211: 210 | B211: BACHILLERATO ORIENTADO | C211: Arte - Teatro | D211: 4 | E211: 4 | F211: Talleres | G211: Teatro Clown: el arte de la risa y la vulnerabilidad B | J211: 4 | K211: Laboratorio de la Orientación B + Taller de la Orientación B | Taller de Artes G + H | L211: Taller | M211: Formación General | Formación Orientada | N211: Bachiller Común A | Bachiller Común B | O211: AGRO Y AMBIENTE | ARTE MUSICA | ARTE TEATRO | ARTES VISUALES | COMUNICACIÓN | CS. NATURALES | CS. SOCIALES Y HUMANIDADES | ECONOMÍA Y ADMINISTRACIÓN | EDUCACIÓN | EDUCACIÓN FÍSICA | ENERGÍA Y SUSTENTABILIDAD | INFORMÁTICA | LENGUAS | LITERATURA | MATEMÁTICA Y FÍSICA | TURISMO | P211: Sí | Q211: Artes || Taller de artes visuales; Artes en contextos históricos; Lenguajes artísticos combinados; EDI || Taller de música; Artes en contextos históricos; Lenguajes artísticos combinados; EDI || Taller de teatro; Artes en contextos históricos; Lenguajes artísticos combinado; EDI
A212: 211 | B212: BACHILLERATO ORIENTADO | C212: Arte - Teatro | D212: 4 | E212: 3 | F212: Talleres | G212: Expresión y contexto en el teatro performático | J212: 4 | K212: Laboratorio de la Orientación B + Taller de la Orientación B | Taller de Artes G + H | L212: Taller | M212: Formación General | Formación Orientada | N212: Bachiller Común A | Bachiller Común B | O212: AGRO Y AMBIENTE | ARTE MUSICA | ARTE TEATRO | ARTES VISUALES | COMUNICACIÓN | CS. NATURALES | CS. SOCIALES Y HUMANIDADES | ECONOMÍA Y ADMINISTRACIÓN | EDUCACIÓN | EDUCACIÓN FÍSICA | ENERGÍA Y SUSTENTABILIDAD | INFORMÁTICA | LENGUAS | LITERATURA | MATEMÁTICA Y FÍSICA | TURISMO | P212: Sí | Q212: Artes || Taller de artes visuales; Artes en contextos históricos; Lenguajes artísticos combinados; EDI || Taller de música; Artes en contextos históricos; Lenguajes artísticos combinados; EDI || Taller de teatro; Artes en contextos históricos; Lenguajes artísticos combinado; EDI
A213: 212 | B213: BACHILLERATO ORIENTADO | C213: Arte - Teatro | D213: 4 | E213: 4 | F213: Talleres | G213: Creación, gestión y expansión del teatro multimedial | J213: 4 | K213: Laboratorio de la Orientación B + Taller de la Orientación B | Taller de Artes G + H | L213: Taller | M213: Formación General | Formación Orientada | N213: Bachiller Común A | Bachiller Común B | O213: AGRO Y AMBIENTE | ARTE MUSICA | ARTE TEATRO | ARTES VISUALES | COMUNICACIÓN | CS. NATURALES | CS. SOCIALES Y HUMANIDADES | ECONOMÍA Y ADMINISTRACIÓN | EDUCACIÓN | EDUCACIÓN FÍSICA | ENERGÍA Y SUSTENTABILIDAD | INFORMÁTICA | LENGUAS | LITERATURA | MATEMÁTICA Y FÍSICA | TURISMO | P213: Sí | Q213: Artes || Taller de artes visuales; Artes en contextos históricos; Lenguajes artísticos combinados; EDI || Taller de música; Artes en contextos históricos; Lenguajes artísticos combinados; EDI || Taller de teatro; Artes en contextos históricos; Lenguajes artísticos combinado; EDI
A214: 213 | B214: BACHILLERATO ORIENTADO | C214: Arte - Teatro | D214: 4 | E214: 3 | F214: Talleres | G214: La esencia del teatro clasico: dramaturgia y escena | J214: 4 | K214: Laboratorio de la Orientación B + Taller de la Orientación B | Taller de Artes G + H | L214: Taller | M214: Formación General | Formación Orientada | N214: Bachiller Común A | Bachiller Común B | O214: AGRO Y AMBIENTE | ARTE MUSICA | ARTE TEATRO | ARTES VISUALES | COMUNICACIÓN | CS. NATURALES | CS. SOCIALES Y HUMANIDADES | ECONOMÍA Y ADMINISTRACIÓN | EDUCACIÓN | EDUCACIÓN FÍSICA | ENERGÍA Y SUSTENTABILIDAD | INFORMÁTICA | LENGUAS | LITERATURA | MATEMÁTICA Y FÍSICA | TURISMO | P214: Sí | Q214: Artes || Taller de artes visuales; Artes en contextos históricos; Lenguajes artísticos combinados; EDI || Taller de música; Artes en contextos históricos; Lenguajes artísticos combinados; EDI || Taller de teatro; Artes en contextos históricos; Lenguajes artísticos combinado; EDI
A215: 214 | B215: BACHILLERATO ORIENTADO | C215: Arte - Teatro | D215: 4 | E215: 4 | F215: Talleres | G215: El teatro clásico en su contexto: influencias y legado | J215: 4 | K215: Laboratorio de la Orientación B + Taller de la Orientación B | Taller de Artes G + H | L215: Taller | M215: Formación General | Formación Orientada | N215: Bachiller Común A | Bachiller Común B | O215: AGRO Y AMBIENTE | ARTE MUSICA | ARTE TEATRO | ARTES VISUALES | COMUNICACIÓN | CS. NATURALES | CS. SOCIALES Y HUMANIDADES | ECONOMÍA Y ADMINISTRACIÓN | EDUCACIÓN | EDUCACIÓN FÍSICA | ENERGÍA Y SUSTENTABILIDAD | INFORMÁTICA | LENGUAS | LITERATURA | MATEMÁTICA Y FÍSICA | TURISMO | P215: Sí | Q215: Artes || Taller de artes visuales; Artes en contextos históricos; Lenguajes artísticos combinados; EDI || Taller de música; Artes en contextos históricos; Lenguajes artísticos combinados; EDI || Taller de teatro; Artes en contextos históricos; Lenguajes artísticos combinado; EDI
... A293: 292 | B293: BACHILLERATO ORIENTADO | C293: Matemática y Física | D293: 5 | E293: 4 | F293: Proyecto final | G293: Proyecto de egreso 4: evaluación y cierre | J293: 5 | K293: Laboratorio de la Orientación C + Taller de la Orientación C | Mat Nivel 5 | Matemática V | L293: Troncal | M293: Formación General | Formación Orientada | N293: Bachiller Común A | Bachiller Común B | Técnica | O293: AGRO Y AMBIENTE | ARTE MUSICA | ARTE TEATRO | ARTES VISUALES | COMUNICACIÓN | CS. NATURALES | CS. SOCIALES Y HUMANIDADES | ECONOMÍA Y ADMINISTRACIÓN | EDUCACIÓN | EDUCACIÓN FÍSICA | ENERGÍA Y SUSTENTABILIDAD | INFORMÁTICA | LENGUAS | LITERATURA | MATEMÁTICA Y FÍSICA | TURISMO | Técnico AUTOMOTORES | Técnico ELECTRICISTA | Técnico MECÁNICO | Técnico MECÁNICO ELECTRICISTA | P293: Sí | Q293: Ciencia en Contexto; Matemática para la Física || Lógica y Filosofía de la Ciencia; Matemática para la Física; historia orientada || Matemática
A294: 293 | B294: BACHILLERATO ORIENTADO | C294: Turismo | D294: 4 | E294: 1 | F294: Laboratorios | G294: Turismo, sociedad y transformaciones A | J294: 4 | L294: Troncal
A295: 294 | B295: BACHILLERATO ORIENTADO | C295: Turismo | D295: 4 | E295: 2 | F295: Laboratorios | G295: Turismo, sociedad y transformaciones B | J295: 4 | L295: Troncal
A296: 295 | B296: BACHILLERATO ORIENTADO | C296: Turismo | D296: 4 | E296: 1 | F296: Laboratorios | G296: ¿Buenos Aires es una ciudad turística? A | J296: 4 | L296: Troncal
A297: 296 | B297: BACHILLERATO ORIENTADO | C297: Turismo | D297: 4 | E297: 2 | F297: Laboratorios | G297: ¿Buenos Aires es una ciudad turística? B | J297: 4 | L297: Troncal
A298: 297 | B298: BACHILLERATO ORIENTADO | C298: Turismo | D298: 4 | E298: 1 | F298: Laboratorios | G298: Destinos turísticos de Argentina: mapas, recorridos y circuito A | J298: 4 | L298: Troncal
A299: 298 | B299: BACHILLERATO ORIENTADO | C299: Turismo | D299: 4 | E299: 2 | F299: Laboratorios | G299: Destinos turísticos de Argentina: mapas, recorridos y circuito B | J299: 4 | L299: Troncal
A300: 299 | B300: BACHILLERATO ORIENTADO | C300: Turismo | D300: 4 | E300: 3 | F300: Talleres | G300: La cocina como elemento identitario cultural A | J300: 4 | L300: Troncal
A301: 300 | B301: BACHILLERATO ORIENTADO | C301: Turismo | D301: 4 | E301: 4 | F301: Talleres | G301: La cocina como elemento identitario cultural B | J301: 4 | L301: Troncal
A302: 301 | B302: BACHILLERATO ORIENTADO | C302: Turismo | D302: 4 | E302: 3 | F302: Talleres | G302: Cómo construyo un producto turístico A | J302: 4 | L302: Troncal
A303: 302 | B303: BACHILLERATO ORIENTADO | C303: Turismo | D303: 4 | E303: 4 | F303: Talleres | G303: Cómo construyo un producto turístico B | J303: 4 | L303: Troncal
A304: 303 | B304: BACHILLERATO ORIENTADO | C304: Turismo | D304: 4 | E304: 3 | F304: Talleres | G304: Diarios de viaje y producción audiovisual A | J304: 4 | L304: Troncal
A305: 304 | B305: BACHILLERATO ORIENTADO | C305: Turismo | D305: 4 | E305: 4 | F305: Talleres | G305: Diarios de viaje y producción audiovisual B | J305: 4 | L305: Troncal
... A308: 307 | B308: BACHILLERATO ORIENTADO | C308: Turismo | D308: 5 | E308: 4 | F308: Proyecto final | G308: Evaluación y cierre del proyecto | J308: 5 | L308: Troncal
A309: 308 | B309: BACHILLERATO ORIENTADO | C309: Música | D309: 4 | E309: 1 | F309: Laboratorios | G309: Música y recursos tecnológicos A | J309: 4 | K309: Laboratorio de la Orientación B + Taller de la Orientación B | Taller de Artes G + H | L309: Taller | M309: Formación General | Formación Orientada | N309: Bachiller Común A | Bachiller Común B | O309: AGRO Y AMBIENTE | ARTE MUSICA | ARTE TEATRO | ARTES VISUALES | COMUNICACIÓN | CS. NATURALES | CS. SOCIALES Y HUMANIDADES | ECONOMÍA Y ADMINISTRACIÓN | EDUCACIÓN | EDUCACIÓN FÍSICA | ENERGÍA Y SUSTENTABILIDAD | INFORMÁTICA | LENGUAS | LITERATURA | MATEMÁTICA Y FÍSICA | TURISMO | P309: Sí | Q309: Artes || Taller de artes visuales; Artes en contextos históricos; Lenguajes artísticos combinados; EDI || Taller de música; Artes en contextos históricos; Lenguajes artísticos combinados; EDI || Taller de teatro; Artes en contextos históricos; Lenguajes artísticos combinado; EDI
A310: 309 | B310: BACHILLERATO ORIENTADO | C310: Música | D310: 4 | E310: 2 | F310: Laboratorios | G310: Música y recursos tecnológicos B | J310: 4 | K310: Laboratorio de la Orientación B + Taller de la Orientación B | Taller de Artes G + H | L310: Taller | M310: Formación General | Formación Orientada | N310: Bachiller Común A | Bachiller Común B | O310: AGRO Y AMBIENTE | ARTE MUSICA | ARTE TEATRO | ARTES VISUALES | COMUNICACIÓN | CS. NATURALES | CS. SOCIALES Y HUMANIDADES | ECONOMÍA Y ADMINISTRACIÓN | EDUCACIÓN | EDUCACIÓN FÍSICA | ENERGÍA Y SUSTENTABILIDAD | INFORMÁTICA | LENGUAS | LITERATURA | MATEMÁTICA Y FÍSICA | TURISMO | P310: Sí | Q310: Artes || Taller de artes visuales; Artes en contextos históricos; Lenguajes artísticos combinados; EDI || Taller de música; Artes en contextos históricos; Lenguajes artísticos combinados; EDI || Taller de teatro; Artes en contextos históricos; Lenguajes artísticos combinado; EDI
A311: 310 | B311: BACHILLERATO ORIENTADO | C311: Música | D311: 4 | E311: 1 | F311: Laboratorios | G311: Paisajes sonoros A | J311: 4 | K311: Laboratorio de la Orientación B + Taller de la Orientación B | Taller de Artes G + H | L311: Taller | M311: Formación General | Formación Orientada | N311: Bachiller Común A | Bachiller Común B | O311: AGRO Y AMBIENTE | ARTE MUSICA | ARTE TEATRO | ARTES VISUALES | COMUNICACIÓN | CS. NATURALES | CS. SOCIALES Y HUMANIDADES | ECONOMÍA Y ADMINISTRACIÓN | EDUCACIÓN | EDUCACIÓN FÍSICA | ENERGÍA Y SUSTENTABILIDAD | INFORMÁTICA | LENGUAS | LITERATURA | MATEMÁTICA Y FÍSICA | TURISMO | P311: Sí | Q311: Artes || Taller de artes visuales; Artes en contextos históricos; Lenguajes artísticos combinados; EDI || Taller de música; Artes en contextos históricos; Lenguajes artísticos combinados; EDI || Taller de teatro; Artes en contextos históricos; Lenguajes artísticos combinado; EDI
A312: 311 | B312: BACHILLERATO ORIENTADO | C312: Música | D312: 4 | E312: 2 | F312: Laboratorios | G312: Paisajes sonoros B | J312: 4 | K312: Laboratorio de la Orientación B + Taller de la Orientación B | Taller de Artes G + H | L312: Taller | M312: Formación General | Formación Orientada | N312: Bachiller Común A | Bachiller Común B | O312: AGRO Y AMBIENTE | ARTE MUSICA | ARTE TEATRO | ARTES VISUALES | COMUNICACIÓN | CS. NATURALES | CS. SOCIALES Y HUMANIDADES | ECONOMÍA Y ADMINISTRACIÓN | EDUCACIÓN | EDUCACIÓN FÍSICA | ENERGÍA Y SUSTENTABILIDAD | INFORMÁTICA | LENGUAS | LITERATURA | MATEMÁTICA Y FÍSICA | TURISMO | P312: Sí | Q312: Artes || Taller de artes visuales; Artes en contextos históricos; Lenguajes artísticos combinados; EDI || Taller de música; Artes en contextos históricos; Lenguajes artísticos combinados; EDI || Taller de teatro; Artes en contextos históricos; Lenguajes artísticos combinado; EDI
A313: 312 | B313: BACHILLERATO ORIENTADO | C313: Música | D313: 4 | E313: 1 | F313: Laboratorios | G313: Explorando el mundo sonoro A | J313: 4 | K313: Laboratorio de la Orientación B + Taller de la Orientación B | Taller de Artes G + H | L313: Taller | M313: Formación General | Formación Orientada | N313: Bachiller Común A | Bachiller Común B | O313: AGRO Y AMBIENTE | ARTE MUSICA | ARTE TEATRO | ARTES VISUALES | COMUNICACIÓN | CS. NATURALES | CS. SOCIALES Y HUMANIDADES | ECONOMÍA Y ADMINISTRACIÓN | EDUCACIÓN | EDUCACIÓN FÍSICA | ENERGÍA Y SUSTENTABILIDAD | INFORMÁTICA | LENGUAS | LITERATURA | MATEMÁTICA Y FÍSICA | TURISMO | P313: Sí | Q313: Artes || Taller de artes visuales; Artes en contextos históricos; Lenguajes artísticos combinados; EDI || Taller de música; Artes en contextos históricos; Lenguajes artísticos combinados; EDI || Taller de teatro; Artes en contextos históricos; Lenguajes artísticos combinado; EDI
A314: 313 | B314: BACHILLERATO ORIENTADO | C314: Música | D314: 4 | E314: 2 | F314: Laboratorios | G314: Explorando el mundo sonoro B | J314: 4 | K314: Laboratorio de la Orientación B + Taller de la Orientación B | Taller de Artes G + H | L314: Taller | M314: Formación General | Formación Orientada | N314: Bachiller Común A | Bachiller Común B | O314: AGRO Y AMBIENTE | ARTE MUSICA | ARTE TEATRO | ARTES VISUALES | COMUNICACIÓN | CS. NATURALES | CS. SOCIALES Y HUMANIDADES | ECONOMÍA Y ADMINISTRACIÓN | EDUCACIÓN | EDUCACIÓN FÍSICA | ENERGÍA Y SUSTENTABILIDAD | INFORMÁTICA | LENGUAS | LITERATURA | MATEMÁTICA Y FÍSICA | TURISMO | P314: Sí | Q314: Artes || Taller de artes visuales; Artes en contextos históricos; Lenguajes artísticos combinados; EDI || Taller de música; Artes en contextos históricos; Lenguajes artísticos combinados; EDI || Taller de teatro; Artes en contextos históricos; Lenguajes artísticos combinado; EDI
A315: 314 | B315: BACHILLERATO ORIENTADO | C315: Música | D315: 4 | E315: 3 | F315: Talleres | G315: De la escucha a la experimentación A | J315: 4 | K315: Laboratorio de la Orientación B + Taller de la Orientación B | Taller de Artes G + H | L315: Taller | M315: Formación General | Formación Orientada | N315: Bachiller Común A | Bachiller Común B | O315: AGRO Y AMBIENTE | ARTE MUSICA | ARTE TEATRO | ARTES VISUALES | COMUNICACIÓN | CS. NATURALES | CS. SOCIALES Y HUMANIDADES | ECONOMÍA Y ADMINISTRACIÓN | EDUCACIÓN | EDUCACIÓN FÍSICA | ENERGÍA Y SUSTENTABILIDAD | INFORMÁTICA | LENGUAS | LITERATURA | MATEMÁTICA Y FÍSICA | TURISMO | P315: Sí | Q315: Artes || Taller de artes visuales; Artes en contextos históricos; Lenguajes artísticos combinados; EDI || Taller de música; Artes en contextos históricos; Lenguajes artísticos combinados; EDI || Taller de teatro; Artes en contextos históricos; Lenguajes artísticos combinado; EDI
A316: 315 | B316: BACHILLERATO ORIENTADO | C316: Música | D316: 4 | E316: 4 | F316: Talleres | G316: De la escucha a la experimentación B | J316: 4 | K316: Laboratorio de la Orientación B + Taller de la Orientación B | Taller de Artes G + H | L316: Taller | M316: Formación General | Formación Orientada | N316: Bachiller Común A | Bachiller Común B | O316: AGRO Y AMBIENTE | ARTE MUSICA | ARTE TEATRO | ARTES VISUALES | COMUNICACIÓN | CS. NATURALES | CS. SOCIALES Y HUMANIDADES | ECONOMÍA Y ADMINISTRACIÓN | EDUCACIÓN | EDUCACIÓN FÍSICA | ENERGÍA Y SUSTENTABILIDAD | INFORMÁTICA | LENGUAS | LITERATURA | MATEMÁTICA Y FÍSICA | TURISMO | P316: Sí | Q316: Artes || Taller de artes visuales; Artes en contextos históricos; Lenguajes artísticos combinados; EDI || Taller de música; Artes en contextos históricos; Lenguajes artísticos combinados; EDI || Taller de teatro; Artes en contextos históricos; Lenguajes artísticos combinado; EDI
A317: 316 | B317: BACHILLERATO ORIENTADO | C317: Música | D317: 4 | E317: 3 | F317: Talleres | G317: De la práctica a la grabación A | J317: 4 | K317: Laboratorio de la Orientación B + Taller de la Orientación B | Taller de Artes G + H | L317: Taller | M317: Formación General | Formación Orientada | N317: Bachiller Común A | Bachiller Común B | O317: AGRO Y AMBIENTE | ARTE MUSICA | ARTE TEATRO | ARTES VISUALES | COMUNICACIÓN | CS. NATURALES | CS. SOCIALES Y HUMANIDADES | ECONOMÍA Y ADMINISTRACIÓN | EDUCACIÓN | EDUCACIÓN FÍSICA | ENERGÍA Y SUSTENTABILIDAD | INFORMÁTICA | LENGUAS | LITERATURA | MATEMÁTICA Y FÍSICA | TURISMO | P317: Sí | Q317: Artes || Taller de artes visuales; Artes en contextos históricos; Lenguajes artísticos combinados; EDI || Taller de música; Artes en contextos históricos; Lenguajes artísticos combinados; EDI || Taller de teatro; Artes en contextos históricos; Lenguajes artísticos combinado; EDI
A318: 317 | B318: BACHILLERATO ORIENTADO | C318: Música | D318: 4 | E318: 4 | F318: Talleres | G318: De la práctica a la grabación B | J318: 4 | K318: Laboratorio de la Orientación B + Taller de la Orientación B | Taller de Artes G + H | L318: Taller | M318: Formación General | Formación Orientada | N318: Bachiller Común A | Bachiller Común B | O318: AGRO Y AMBIENTE | ARTE MUSICA | ARTE TEATRO | ARTES VISUALES | COMUNICACIÓN | CS. NATURALES | CS. SOCIALES Y HUMANIDADES | ECONOMÍA Y ADMINISTRACIÓN | EDUCACIÓN | EDUCACIÓN FÍSICA | ENERGÍA Y SUSTENTABILIDAD | INFORMÁTICA | LENGUAS | LITERATURA | MATEMÁTICA Y FÍSICA | TURISMO | P318: Sí | Q318: Artes || Taller de artes visuales; Artes en contextos históricos; Lenguajes artísticos combinados; EDI || Taller de música; Artes en contextos históricos; Lenguajes artísticos combinados; EDI || Taller de teatro; Artes en contextos históricos; Lenguajes artísticos combinado; EDI
A319: 318 | B319: BACHILLERATO ORIENTADO | C319: Música | D319: 4 | E319: 3 | F319: Talleres | G319: De la creación a la gestión A | J319: 4 | K319: Laboratorio de la Orientación B + Taller de la Orientación B | Taller de Artes G + H | L319: Taller | M319: Formación General | Formación Orientada | N319: Bachiller Común A | Bachiller Común B | O319: AGRO Y AMBIENTE | ARTE MUSICA | ARTE TEATRO | ARTES VISUALES | COMUNICACIÓN | CS. NATURALES | CS. SOCIALES Y HUMANIDADES | ECONOMÍA Y ADMINISTRACIÓN | EDUCACIÓN | EDUCACIÓN FÍSICA | ENERGÍA Y SUSTENTABILIDAD | INFORMÁTICA | LENGUAS | LITERATURA | MATEMÁTICA Y FÍSICA | TURISMO | P319: Sí | Q319: Artes || Taller de artes visuales; Artes en contextos históricos; Lenguajes artísticos combinados; EDI || Taller de música; Artes en contextos históricos; Lenguajes artísticos combinados; EDI || Taller de teatro; Artes en contextos históricos; Lenguajes artísticos combinado; EDI
A320: 319 | B320: BACHILLERATO ORIENTADO | C320: Música | D320: 4 | E320: 4 | F320: Talleres | G320: De la creación a la gestión B | J320: 4 | K320: Laboratorio de la Orientación B + Taller de la Orientación B | Taller de Artes G + H | L320: Taller | M320: Formación General | Formación Orientada | N320: Bachiller Común A | Bachiller Común B | O320: AGRO Y AMBIENTE | ARTE MUSICA | ARTE TEATRO | ARTES VISUALES | COMUNICACIÓN | CS. NATURALES | CS. SOCIALES Y HUMANIDADES | ECONOMÍA Y ADMINISTRACIÓN | EDUCACIÓN | EDUCACIÓN FÍSICA | ENERGÍA Y SUSTENTABILIDAD | INFORMÁTICA | LENGUAS | LITERATURA | MATEMÁTICA Y FÍSICA | TURISMO | P320: Sí | Q320: Artes || Taller de artes visuales; Artes en contextos históricos; Lenguajes artísticos combinados; EDI || Taller de música; Artes en contextos históricos; Lenguajes artísticos combinados; EDI || Taller de teatro; Artes en contextos históricos; Lenguajes artísticos combinado; EDI
... A323: 322 | B323: BACHILLERATO ORIENTADO | C323: Música | D323: 5 | E323: 4 | F323: Proyecto final | G323: Reflexión y evaluación del proyecto musical | J323: 5 | K323: Laboratorio de la Orientación C + Taller de la Orientación C | Proyecto de Vinculación con el Futuro | L323: Taller | M323: Formación General | Formación Orientada | N323: Bachiller Común A | Bachiller Común B | O323: ARTE MUSICA | ARTE TEATRO | ARTES VISUALES | P323: Sí | Q323: Arte público y producción colectiva; Arte cultura y sociedad; Artes visuales y multimedia || Arte público y producción colectiva; Arte cultura y sociedad; Artes visuales y multimedia; Historia orientada || Improvisación y ensambles musicales; Arte, cultura y sociedad; Artes visuales y multimedia; Historia orientada || Improvisación y ensambles musicales; Historia de las artes; Artes visuales y multimedia || Producción en artes escénicas y gestión cultural; Tecnologías de la información orientada
A324: 323 | B324: BACHILLERATO ORIENTADO | C324: Economía y admin. | D324: 4 | E324: 1 | F324: Laboratorios | G324: Estrategias organizacionales frente al desempleo juvenil A | J324: 4 | L324: Troncal
A325: 324 | B325: BACHILLERATO ORIENTADO | C325: Economía y admin. | D325: 4 | E325: 2 | F325: Laboratorios | G325: Estrategias organizacionales frente al desempleo juvenil B | J325: 4 | L325: Troncal
A326: 325 | B326: BACHILLERATO ORIENTADO | C326: Economía y admin. | D326: 4 | E326: 1 | F326: Laboratorios | G326: Adaptar la administración a los desafíos actuales A | J326: 4 | L326: Troncal
A327: 326 | B327: BACHILLERATO ORIENTADO | C327: Economía y admin. | D327: 4 | E327: 2 | F327: Laboratorios | G327: Adaptar la administración a los desafíos actuales B | J327: 4 | L327: Troncal
A328: 327 | B328: BACHILLERATO ORIENTADO | C328: Economía y admin. | D328: 4 | E328: 1 | F328: Laboratorios | G328: Presupuesto público y participación ciudadana A | J328: 4 | L328: Troncal
A329: 328 | B329: BACHILLERATO ORIENTADO | C329: Economía y admin. | D329: 4 | E329: 2 | F329: Laboratorios | G329: Presupuesto público y participación ciudadana B | J329: 4 | L329: Troncal
A330: 329 | B330: BACHILLERATO ORIENTADO | C330: Economía y admin. | D330: 4 | E330: 3 | F330: Talleres | G330: Gestión integral del capital humano A | J330: 4 | L330: Troncal
A331: 330 | B331: BACHILLERATO ORIENTADO | C331: Economía y admin. | D331: 4 | E331: 4 | F331: Talleres | G331: Gestión integral del capital humano B | J331: 4 | L331: Troncal
A332: 331 | B332: BACHILLERATO ORIENTADO | C332: Economía y admin. | D332: 4 | E332: 3 | F332: Talleres | G332: Sistemas de administración A | J332: 4 | L332: Troncal
A333: 332 | B333: BACHILLERATO ORIENTADO | C333: Economía y admin. | D333: 4 | E333: 4 | F333: Talleres | G333: Sistemas de administración B | J333: 4 | L333: Troncal
A334: 333 | B334: BACHILLERATO ORIENTADO | C334: Economía y admin. | D334: 4 | E334: 3 | F334: Talleres | G334: Gestión de marketing A | J334: 4 | L334: Troncal
A335: 334 | B335: BACHILLERATO ORIENTADO | C335: Economía y admin. | D335: 4 | E335: 4 | F335: Talleres | G335: Gestión de marketing B | J335: 4 | L335: Troncal
... A338: 337 | B338: BACHILLERATO ORIENTADO | C338: Economía y admin. | D338: 5 | E338: 4 | F338: Proyecto final | G338: Proyecto de egreso 4: Análisis del proceso y resultados | J338: 5 | L338: Troncal
A339: 338 | B339: BACHILLERATO ORIENTADO | C339: Informática | D339: 4 | E339: 1 | F339: Laboratorios | G339: Diseño y creación de bases de datos | J339: 4 | K339: Espacios de Integración de Especialidad I + Espacios de Integración de Especialidad II | Laboratorio de la Orientación B + Taller de la Orientación B | Taller de Tecnología E + F | L339: Taller | M339: Formación General | Formación Orientada | N339: Bachiller Común A | Bachiller Común B | Técnica | O339: AGRO Y AMBIENTE | ARTE MUSICA | ARTE TEATRO | ARTES VISUALES | COMUNICACIÓN | CS. NATURALES | CS. SOCIALES Y HUMANIDADES | ECONOMÍA Y ADMINISTRACIÓN | EDUCACIÓN | EDUCACIÓN FÍSICA | ENERGÍA Y SUSTENTABILIDAD | INFORMÁTICA | LENGUAS | LITERATURA | MATEMÁTICA Y FÍSICA | TURISMO | Técnico MECÁNICO | Técnico MECÁNICO ELECTRICISTA | Técnico ÓPTICA OFTALMICA E INSTRUMENTAL | Técnico GEÓGRAFO MATEMATICO | P339: Sí | Q339: --Circuitos eléctricos y magnéticos; --Dispositivos electrónicos; --Lab de Mediciones Eléctricas 1; --Tecnología de los materiales; --Mecánica técnica; --Representación gráfica || Ciencia en Contexto; Laboratorio de Matemática; Física y Tecnología; EDI || Dibujo mecánico 1; Hidráulica industrial; electrotecnia; química aplicada; tecnología de los materiales; mecánica técnica || Ecología; Filosofía de la ciencia y tecnología; EDI || Estructura del Universo; Filosofia de la ciencia y la tecnología
A340: 339 | B340: BACHILLERATO ORIENTADO | C340: Informática | D340: 4 | E340: 2 | F340: Laboratorios | G340: La base está, ¿pero quién la tiene? | J340: 4 | K340: Espacios de Integración de Especialidad I + Espacios de Integración de Especialidad II | Laboratorio de la Orientación B + Taller de la Orientación B | Taller de Tecnología E + F | L340: Taller | M340: Formación General | Formación Orientada | N340: Bachiller Común A | Bachiller Común B | Técnica | O340: AGRO Y AMBIENTE | ARTE MUSICA | ARTE TEATRO | ARTES VISUALES | COMUNICACIÓN | CS. NATURALES | CS. SOCIALES Y HUMANIDADES | ECONOMÍA Y ADMINISTRACIÓN | EDUCACIÓN | EDUCACIÓN FÍSICA | ENERGÍA Y SUSTENTABILIDAD | INFORMÁTICA | LENGUAS | LITERATURA | MATEMÁTICA Y FÍSICA | TURISMO | Técnico MECÁNICO | Técnico MECÁNICO ELECTRICISTA | Técnico ÓPTICA OFTALMICA E INSTRUMENTAL | Técnico GEÓGRAFO MATEMATICO | P340: Sí | Q340: --Circuitos eléctricos y magnéticos; --Dispositivos electrónicos; --Lab de Mediciones Eléctricas 1; --Tecnología de los materiales; --Mecánica técnica; --Representación gráfica || Ciencia en Contexto; Laboratorio de Matemática; Física y Tecnología; EDI || Dibujo mecánico 1; Hidráulica industrial; electrotecnia; química aplicada; tecnología de los materiales; mecánica técnica || Ecología; Filosofía de la ciencia y tecnología; EDI || Estructura del Universo; Filosofia de la ciencia y la tecnología
A341: 340 | B341: BACHILLERATO ORIENTADO | C341: Informática | D341: 4 | E341: 1 | F341: Laboratorios | G341: De los fichines al metaverso A | J341: 4 | K341: Espacios de Integración de Especialidad I + Espacios de Integración de Especialidad II | Laboratorio de la Orientación B + Taller de la Orientación B | Taller de Tecnología E + F | L341: Taller | M341: Formación General | Formación Orientada | N341: Bachiller Común A | Bachiller Común B | Técnica | O341: AGRO Y AMBIENTE | ARTE MUSICA | ARTE TEATRO | ARTES VISUALES | COMUNICACIÓN | CS. NATURALES | CS. SOCIALES Y HUMANIDADES | ECONOMÍA Y ADMINISTRACIÓN | EDUCACIÓN | EDUCACIÓN FÍSICA | ENERGÍA Y SUSTENTABILIDAD | INFORMÁTICA | LENGUAS | LITERATURA | MATEMÁTICA Y FÍSICA | TURISMO | Técnico MECÁNICO | Técnico MECÁNICO ELECTRICISTA | Técnico ÓPTICA OFTALMICA E INSTRUMENTAL | Técnico GEÓGRAFO MATEMATICO | P341: Sí | Q341: --Circuitos eléctricos y magnéticos; --Dispositivos electrónicos; --Lab de Mediciones Eléctricas 1; --Tecnología de los materiales; --Mecánica técnica; --Representación gráfica || Ciencia en Contexto; Laboratorio de Matemática; Física y Tecnología; EDI || Dibujo mecánico 1; Hidráulica industrial; electrotecnia; química aplicada; tecnología de los materiales; mecánica técnica || Ecología; Filosofía de la ciencia y tecnología; EDI || Estructura del Universo; Filosofia de la ciencia y la tecnología
A342: 341 | B342: BACHILLERATO ORIENTADO | C342: Informática | D342: 4 | E342: 2 | F342: Laboratorios | G342: De los fichines al metaverso B | J342: 4 | K342: Espacios de Integración de Especialidad I + Espacios de Integración de Especialidad II | Laboratorio de la Orientación B + Taller de la Orientación B | Taller de Tecnología E + F | L342: Taller | M342: Formación General | Formación Orientada | N342: Bachiller Común A | Bachiller Común B | Técnica | O342: AGRO Y AMBIENTE | ARTE MUSICA | ARTE TEATRO | ARTES VISUALES | COMUNICACIÓN | CS. NATURALES | CS. SOCIALES Y HUMANIDADES | ECONOMÍA Y ADMINISTRACIÓN | EDUCACIÓN | EDUCACIÓN FÍSICA | ENERGÍA Y SUSTENTABILIDAD | INFORMÁTICA | LENGUAS | LITERATURA | MATEMÁTICA Y FÍSICA | TURISMO | Técnico MECÁNICO | Técnico MECÁNICO ELECTRICISTA | Técnico ÓPTICA OFTALMICA E INSTRUMENTAL | Técnico GEÓGRAFO MATEMATICO | P342: Sí | Q342: --Circuitos eléctricos y magnéticos; --Dispositivos electrónicos; --Lab de Mediciones Eléctricas 1; --Tecnología de los materiales; --Mecánica técnica; --Representación gráfica || Ciencia en Contexto; Laboratorio de Matemática; Física y Tecnología; EDI || Dibujo mecánico 1; Hidráulica industrial; electrotecnia; química aplicada; tecnología de los materiales; mecánica técnica || Ecología; Filosofía de la ciencia y tecnología; EDI || Estructura del Universo; Filosofia de la ciencia y la tecnología
A343: 342 | B343: BACHILLERATO ORIENTADO | C343: Informática | D343: 4 | E343: 1 | F343: Laboratorios | G343: Aplicaciones para la vida con IA - A | J343: 4 | K343: Espacios de Integración de Especialidad I + Espacios de Integración de Especialidad II | Laboratorio de la Orientación B + Taller de la Orientación B | Taller de Tecnología E + F | L343: Taller | M343: Formación General | Formación Orientada | N343: Bachiller Común A | Bachiller Común B | Técnica | O343: AGRO Y AMBIENTE | ARTE MUSICA | ARTE TEATRO | ARTES VISUALES | COMUNICACIÓN | CS. NATURALES | CS. SOCIALES Y HUMANIDADES | ECONOMÍA Y ADMINISTRACIÓN | EDUCACIÓN | EDUCACIÓN FÍSICA | ENERGÍA Y SUSTENTABILIDAD | INFORMÁTICA | LENGUAS | LITERATURA | MATEMÁTICA Y FÍSICA | TURISMO | Técnico MECÁNICO | Técnico MECÁNICO ELECTRICISTA | Técnico ÓPTICA OFTALMICA E INSTRUMENTAL | Técnico GEÓGRAFO MATEMATICO | P343: Sí | Q343: --Circuitos eléctricos y magnéticos; --Dispositivos electrónicos; --Lab de Mediciones Eléctricas 1; --Tecnología de los materiales; --Mecánica técnica; --Representación gráfica || Ciencia en Contexto; Laboratorio de Matemática; Física y Tecnología; EDI || Dibujo mecánico 1; Hidráulica industrial; electrotecnia; química aplicada; tecnología de los materiales; mecánica técnica || Ecología; Filosofía de la ciencia y tecnología; EDI || Estructura del Universo; Filosofia de la ciencia y la tecnología
A344: 343 | B344: BACHILLERATO ORIENTADO | C344: Informática | D344: 4 | E344: 2 | F344: Laboratorios | G344: Aplicaciones para la vida con IA - B | J344: 4 | K344: Espacios de Integración de Especialidad I + Espacios de Integración de Especialidad II | Laboratorio de la Orientación B + Taller de la Orientación B | Taller de Tecnología E + F | L344: Taller | M344: Formación General | Formación Orientada | N344: Bachiller Común A | Bachiller Común B | Técnica | O344: AGRO Y AMBIENTE | ARTE MUSICA | ARTE TEATRO | ARTES VISUALES | COMUNICACIÓN | CS. NATURALES | CS. SOCIALES Y HUMANIDADES | ECONOMÍA Y ADMINISTRACIÓN | EDUCACIÓN | EDUCACIÓN FÍSICA | ENERGÍA Y SUSTENTABILIDAD | INFORMÁTICA | LENGUAS | LITERATURA | MATEMÁTICA Y FÍSICA | TURISMO | Técnico MECÁNICO | Técnico MECÁNICO ELECTRICISTA | Técnico ÓPTICA OFTALMICA E INSTRUMENTAL | Técnico GEÓGRAFO MATEMATICO | P344: Sí | Q344: --Circuitos eléctricos y magnéticos; --Dispositivos electrónicos; --Lab de Mediciones Eléctricas 1; --Tecnología de los materiales; --Mecánica técnica; --Representación gráfica || Ciencia en Contexto; Laboratorio de Matemática; Física y Tecnología; EDI || Dibujo mecánico 1; Hidráulica industrial; electrotecnia; química aplicada; tecnología de los materiales; mecánica técnica || Ecología; Filosofía de la ciencia y tecnología; EDI || Estructura del Universo; Filosofia de la ciencia y la tecnología
...

Sheet MateriaContenido
A1: ID_MateriaContenido | B1: MateriaID | C1: NombreMateria | D1: ContenidoID | E1: TituloPlan/NombreContenido | F1: Nivel | G1: Bimestre | H1: TipoCursada | I1: CategoriaPCI | J1: CategoriaFormacion | K1: Modalidad_Tipo | L1: EsCompuesta | M1: EspecialidadID | N1: MateriasAgrupadas | O1: ContenidosPriorizadosID | P1: Enlaces | Q1: Activo
B2: 1 | C2: Matemática | D2: 1 | E2: Números naturales y enteros | F2: 1 | G2: 1 | H2: Obligatorio | I2: Troncal | J2: Formación General | K2: Bachiller Común A | L2: No | M2: 101 | N2: (vacío) | P2: (link) | Q2: Sí

Sheet Contenidos_priorizados
A1: ContenidoPriorizadoID | B1: NombreContenidoPriorizado | C1: MateriaID | D1: EspecialidadID | E1: Modalidad_Tipo | F1: TipoCursada | G1: CategoriaPCI | H1: CategoriaFormacion | I1: Enlaces | J1: Activo
A2: 1 | B2: Números enteros | C2: 1 | D2: 101 | E2: Bachiller Común A | F2: Obligatorio | G2: Troncal | H2: Formación General | I2: (link) | J2: Sí
A3: 2 | B3: Gráficos cartesianos | C3: 2 | D3: 101 | E3: Bachiller Común B

Sheet CONTENIDOS_Proveedor
A1: ID_Contenido_producido | B1: Nombre_Contenido | C1: ID_Materia | D1: Nombre_Materia | E1: Materia_hoja | F1: Anio | G1: Es_Troncal | H1: Es_Prioritario | I1: Eje_Tematico | J1: Activo | K1: Observaciones
A2: 1 | B2: Evolución | E2: Biología | G2: TRUE | H2: TRUE | I2: Eje Principal | J2: TRUE
A3: 2 | B3: Célula. Información genética | E3: Biología | G3: TRUE | H3: TRUE | I3: Eje Principal | J3: TRUE
A4: 3 | B4: Cuerpo humano | E4: Biología | G4: TRUE | H4: TRUE | I4: Eje Principal | J4: TRUE
A5: 4 | B5: Ecología | E5: Biología | G5: TRUE | H5: TRUE | I5: Eje Principal | J5: TRUE
A6: 5 | B6: LA ESTRUCTURA DE LA MATERIA | E6: Química | G6: TRUE | H6: TRUE | I6: Eje Principal | J6: TRUE
A7: 6 | B7: LA MATERIA Y LA CIENCIA QUÍMICA | E7: Química | G7: TRUE | H7: TRUE | I7: Eje Principal | J7: TRUE
A8: 7 | B8: LAS SUSTANCIAS Y LOS CAMBIOS | E8: Química | G8: TRUE | H8: TRUE | I8: Eje Principal | J8: TRUE
A9: 8 | B9: ENERGÍA Y CINÉTICA DE LOS CAMBIOS | E9: Química | G9: TRUE | H9: TRUE | I9: Eje Principal | J9: TRUE
A10: 9 | B10: RELACIONES CUANTITATIVAS EN LA QUÍMICA | E10: Química | G10: TRUE | H10: TRUE | I10: Eje Principal | J10: TRUE
A11: 10 | B11: PROCEDIMIENTOS EN LAS CIENCIAS NATURALES (eje transversal) | E11: Química | G11: TRUE | H11: TRUE | I11: Eje Principal | J11: TRUE
A12: 11 | B12: LA QUÍMICA Y SU INCIDENCIA EN LA SOCIEDAD (eje transversal) | E12: Química | G12: TRUE | H12: TRUE | I12: Eje Principal | J12: TRUE
A13: 12 | B13: PARTÍCULAS | E13: Física | G13: TRUE | H13: TRUE | I13: Eje Principal | J13: TRUE
... A32: 31 | B32: NOCIONES DE FINANZAS PÚBLICAS | E32: Economía | G32: TRUE | H32: TRUE | I32: Eje Principal | J32: TRUE
